Workbook

Sheet primary_studies
A1: ID | B1: TITLE | C1: AUTHORS | D1: YEAR | E1: DOI
A2: P01 | B2: Sustainability Design and Software: The Karlskrona Manifesto | C2: Christoph Becker, Ruzanna Chitchyan, Leticia Duboc, Steve Easterbrook, Birgit Penzenstadler, Norbert Seyff, Colin C. Venters | D2: 2015 | E2: 10.1109/icse.2015.179
A3: P02 | B3: Interdisciplinary Design Patterns for Socially Aware Computing | C3: Harun Baraki, Kurt Geihs, Christian Voigtmann, Axel Hoffmann, Romy Kniewel, Bjo ̈rn-Elmar Macek and Julia Zirfas | D3: 2015 | E3: 10.1109/icse-seis.2019.00010
A4: P03 | B4: The role of design thinking and physical prototyping in social software engineering | C4: Peter Newman, Maria Angela Ferrario, Will Simm, Stephen Forshaw, Adrian Friday, Jon Whittle | D4: 2015 | E4: 10.1145/2889160.2889219
A5: P04 | B5: On the role of value sensitive concerns in software engineering practice | C5: Balbir Barn, Ravinder Barn, Franco Raimondi​ | D5: 2015 | E5: 10.1145/3183428.3183437
A6: P05 | B6: Engineering sustainability through language | C6: Ruzanna Chitchyan, Walter Cazzola, Awais Rashid​​ | D6: 2015 | E6: 10.1109/icse-seis.2019.00015
A7: P06 | B7: Enabling the definition and enforcement of governance rules in open source systems | C7: Javier Luis Cánovas Izquierdo, Jordi Cabot | D7: 2015 | E7: 10.1145/3183428.3183436
A8: P07 | B8: AppCivist: a service-oriented software platform for socially sustainable activism | C8: Animesh Pathak, Valerie Issarny, James Holston​ | D8: 2015
A9: P08 | B9: SOA4DM: applying an SOA paradigm to coordination in humanitarian disaster response | C9: Kelly Lyons, Christie Oh | D9: 2015 | E9: 10.1109/icse-seis.2019.00014
A10: P09 | B10: Managing emergent ethical concerns for software engineering in society | C10: Awais Rashid, Karenza Moore, Corinne May-Chahal, Ruzanna Chitchyan | D10: 2015 | E10: 10.1109/icse.2015.181
A11: P10 | B11: Dementia and social sustainability: challenges for software engineering | C11: Alistair Sutcliffe, Paul Rayson, Chris Bull, Pete Sawyer | D11: 2015 | E11: 10.1109/icse-seis.2017.2
A12: P11 | B12: Cognitively sustainable ICT with ubiquitous mobile services: challenges and opportunities | C12: Marcus Jägemar, Gordana Dodig Crnkovic​ | D12: 2015 | E12: 10.1109/icse-seis.2017.3
A13: P12 | B13: Software energy profiling: comparing releases of a software product | C13: Erik A. Jagroep, Jan Martijn van der Werf, Giuseppe Procaccianti, Patricia Lago, Sjaak Brinkkemper, Leen Blom, Rob van Vliet | D13: 2016 | E13: 10.1145/3377815.3381377
A14: P13 | B14: Sustainability design in requirements engineering: state of practice | C14: Ruzanna Chitchyan, Walter Cazzola, Awais Rashid | D14: 2016 | E14: 10.1109/icse-seis52602.2021.00012
A15: P14 | B15: Sustainability debt: a portfolio-based approach for evaluating sustainability requirements in architectures | C15: Javier Garbajosa, José Ángel Sanz, Mikael Svahnberg, Jan Bosch | D15: 2016 | E15: 10.1109/icse-seis.2019.00012
A16: P15 | B16: Values-first SE: research principles in practice | C16: Maria Paasivaara, Casper Lassenius, Steven Fraser, Jürgen Münch, Kari Systä | D16: 2016 | E16: 10.1145/2889160.2889216
A17: P16 | B17: A guided tour of the legal implications of software cloning | C17: Paolo Ciancarini, Daniel Russo, Alberto Sillitti, Giancarlo Succi | D17: 2016 | E17: 10.1109/icse-seis.2019.00011
A18: P17 | B18: Engineering software assemblies for participatory democracy: the participatory budgeting use case | C18: James Holston, Valérie Issarny, Cristhian Parra | D18: 2016 | E18: 10.1109/icse-seis.2017.8
A19: P18 | B19: Software engineering and policy | C19: Anthony Finkelstein | D19: 2016 | E19: 10.1145/3183428.3183434
A20: P19 | B20: Characterising Sustainability Requirements: A New Species Red Herring or Just an Odd Fish? | C20: Colin C. Venters, Norbert Seyff, Christoph Becker, Stefanie Betz, Ruzanna Chitchyan, Leticia Duboc, Dan McIntyre, Birgit Penzenstadler | D20: 2017 | E20: 10.1145/2889160.2889221
... A124: P123 | B124: What Can Requirements Engineering Do for Emerging System of Systems? Case of Smart Local Energy | C124: R. Chitchyan | D124: 2024 | E124: 10.1145/3639475.3640108

Sheet citation_data
A1: ID | B1: TITLE | C1: YEAR | D1: DOI | E1: CITATIONS (SORTED)
A2: P01 | B2: Sustainability Design and Software: The Karlskrona Manifesto | C2: 2015 | D2: 10.1109/icse.2015.179 | E2: 130
A3: P40 | B3: Gender Diversity and Women in Software Teams: How Do They Affect Community Smells? | C3: 2019 | D3: 10.1109/icse-seis.2019.00010 | E3: 87
A4: P15 | B4: Values-first SE: research principles in practice | C4: 2016 | D4: 10.1145/2889160.2889219 | E4: 38
A5: P38 | B5: Competence-Confidence Gap: A Threat to Female Developers' Contribution on GitHub | C5: 2018 | D5: 10.1145/3183428.3183437 | E5: 33
A6: P45 | B6: Architecture Design Decision Maps for Software Sustainability | C6: 2019 | D6: 10.1109/icse-seis.2019.00015 | E6: 29
A7: P30 | B7: User Feedback in the App Store: A Cross-Cultural Study | C7: 2018 | D7: 10.1145/3183428.3183436 | E7: 28
A8: P57 | B8: Society-Oriented Applications Development: Investigating Users' Values from Bangladeshi Agriculture Mobile Applications | C8: 2020 | D8: 10.1145/3377815.3381382 | E8: 28
A9: P44 | B9: Beyond the Code Itself: How Programmers Really Look at Pull Requests | C9: 2019 | D9: 10.1109/icse-seis.2019.00014 | E9: 26
A10: P03 | B10: The role of design thinking and physical prototyping in social software engineering | C10: 2015 | D10: 10.1109/icse.2015.181 | E10: 21
A11: P19 | B11: Characterising Sustainability Requirements: A New Species Red Herring or Just an Odd Fish? | C11: 2017 | D11: 10.1109/icse-seis.2017.2 | E11: 21
A12: P20 | B12: Privacy Requirements: Present & Future | C12: 2017 | D12: 10.1109/icse-seis.2017.3 | E12: 21
A13: P55 | B13: Is Using Deep Learning Frameworks Free? Characterizing Technical Debt in Deep Learning Frameworks | C13: 2020 | D13: 10.1145/3377815.3381377 | E13: 21
... A124: P123 | B124: What Can Requirements Engineering Do for Emerging System of Systems? Case of Smart Local Energy | C124: 2024 | D124: 10.1145/3639475.3640108 | E124: 0

Sheet citation_pivot_table
A1: Year | B1: Citations
A2: 2015 | B2: 198
A3: 2016 | B3: 88
A4: 2017 | B4: 91
A5: 2018 | B5: 130
A6: 2019 | B6: 181
A7: 2020 | B7: 100
A8: 2021 | B8: 83
A9: 2022 | B9: 48
A10: 2023 | B10: 33
A11: 2024 | B11: 8
A12: (blank)
A13: Grand Total | B13: 960

Sheet research_type
A1: ID | B1: TITLE | C1: AUTHORS | D1: YEAR | E1: TYPE | F1: REASON | H1: Total Papers | I1: Type | J1: 2015 | K1: 2016 | L1: 2017 | M1: 2018 | N1: 2019 | O1: 2020 | P1: 2021 | Q1: 2022 | R1: 2023 | S1: 2024
A2: P01 | B2: Sustainability Design and Software: The Karlskrona Manifesto | C2: Christoph Becker, Ruzanna Chitchyan, Leticia Duboc, Steve Easterbrook, Birgit Penzenstadler, Norbert Seyff, Colin C. Venters | D2: 2015 | E2: Evaluation Research | F2: Assesses the acceptance and efficacy of green software engineering methods, classifying it as evaluation research. | H2: 46 | I2: Evaluation Research | J2: =COUNTIFS(E:E, I2,D:D,$J$1) -> 4 | K2: =COUNTIFS(E:E, I2,D:D,$K$1) -> 2 | L2: =COUNTIFS(E:E, I2,D:D,$L$1) -> 4 | M2: =COUNTIFS(E:E, I2,D:D,$M$1) -> 5 | N2: =COUNTIFS(E:E, I2,D:D,$N$1) -> 2 | O2: =COUNTIFS(E:E, I2,D:D,$O$1) -> 3 | P2: =COUNTIFS(E:E, I2,D:D,$P$1) -> 2 | Q2: =COUNTIFS(E:E, I2,D:D,$Q$1) -> 7 | R2: =COUNTIFS(E:E, I2,D:D,$R$1) -> 5 | S2: =COUNTIFS(E:E, I2,D:D,$S$1) -> 13
A3: P02 | B3: Interdisciplinary Design Patterns for Socially Aware Computing | C3: Harun Baraki, Kurt Geihs, Christian Voigtmann, Axel Hoffmann, Romy Kniewel, Bjo ̈rn-Elmar Macek and Julia Zirfas | D3: 2015 | E3: Proposal of Solution | F3: Provides design patterns for incorporating social awareness into computing systems, hence proposing a solution. | H3: 38 | I3: Proposal of Solution | J3: =COUNTIFS(E:E, I3,D:D,$J$1) -> 5 | K3: =COUNTIFS(E:E, I3,D:D,$K$1) -> 1 | L3: =COUNTIFS(E:E, I3,D:D,$L$1) -> 3 | M3: =COUNTIFS(E:E, I3,D:D,$M$1) -> 4 | N3: =COUNTIFS(E:E, I3,D:D,$N$1) -> 2 | O3: =COUNTIFS(E:E, I3,D:D,$O$1) -> 2 | P3: =COUNTIFS(E:E, I3,D:D,$P$1) -> 5 | Q3: =COUNTIFS(E:E, I3,D:D,$Q$1) -> 5 | R3: =COUNTIFS(E:E, I3,D:D,$R$1) -> 6 | S3: 5
A4: P03 | B4: The role of design thinking and physical prototyping in social software engineering | C4: Peter Newman, Maria Angela Ferrario, Will Simm, Stephen Forshaw, Adrian Friday, Jon Whittle | D4: 2015 | E4: Evaluation Research | F4: This paper evaluates the impact of software engineering practices on many areas of sustainability, and it is classified as evaluation research. | H4: 5 | I4: Opinion Paper | J4: =COUNTIFS(E:E, I4,D:D,$J$1) -> 1 | K4: =COUNTIFS(E:E, I4,D:D,$K$1) -> 1 | L4: =COUNTIFS(E:E, I4,D:D,$L$1) -> 0 | M4: =COUNTIFS(E:E, I4,D:D,$M$1) -> 0 | N4: =COUNTIFS(E:E, I4,D:D,$N$1) -> 0 | O4: =COUNTIFS(E:E, I4,D:D,$O$1) -> 1 | P4: =COUNTIFS(E:E, I4,D:D,$P$1) -> 0 | Q4: =COUNTIFS(E:E, I4,D:D,$Q$1) -> 2 | R4: =COUNTIFS(E:E, I4,D:D,$R$1) -> 0 | S4: 0
A5: P04 | B5: On the role of value sensitive concerns in software engineering practice | C5: Balbir Barn, Ravinder Barn, Franco Raimondi​ | D5: 2015 | E5: Evaluation Research | F5: This article analyzes the role of value-sensitive issues in software engineering practice. It falls under evaluation research because it investigates a problem in practice and its implications. | H5: 10 | I5: Philosophical Paper | J5: =COUNTIFS(E:E, I5,D:D,$J$1) -> 1 | K5: =COUNTIFS(E:E, I5,D:D,$K$1) -> 2 | L5: =COUNTIFS(E:E, I5,D:D,$L$1) -> 0 | M5: =COUNTIFS(E:E, I5,D:D,$M$1) -> 0 | N5: =COUNTIFS(E:E, I5,D:D,$N$1) -> 1 | O5: =COUNTIFS(E:E, I5,D:D,$O$1) -> 1 | P5: =COUNTIFS(E:E, I5,D:D,$P$1) -> 2 | Q5: =COUNTIFS(E:E, I5,D:D,$Q$1) -> 1 | R5: =COUNTIFS(E:E, I5,D:D,$R$1) -> 2 | S5: 0
A6: P05 | B6: Engineering sustainability through language | C6: Ruzanna Chitchyan, Walter Cazzola, Awais Rashid​​ | D6: 2015 | E6: Proposal of Solution | F6: This paper proposes introducing sustainability considerations into programming languages as a solution. | H6: 18 | I6: Validation Research | J6: =COUNTIFS(E:E, I6,D:D,$J$1) -> 0 | K6: =COUNTIFS(E:E, I6,D:D,$K$1) -> 1 | L6: =COUNTIFS(E:E, I6,D:D,$L$1) -> 1 | M6: =COUNTIFS(E:E, I6,D:D,$M$1) -> 2 | N6: =COUNTIFS(E:E, I6,D:D,$N$1) -> 1 | O6: =COUNTIFS(E:E, I6,D:D,$O$1) -> 4 | P6: =COUNTIFS(E:E, I6,D:D,$P$1) -> 2 | Q6: =COUNTIFS(E:E, I6,D:D,$Q$1) -> 2 | R6: =COUNTIFS(E:E, I6,D:D,$R$1) -> 4 | S6: 1
A7: P06 | B7: Enabling the definition and enforcement of governance rules in open source systems | C7: Javier Luis Cánovas Izquierdo, Jordi Cabot | D7: 2015 | E7: Proposal of Solution | F7: This document proposes a governance framework for sustainable software engineering and serves as a solution. | H7: 6 | I7: Personal Experience Paper | J7: =COUNTIFS(E:E, I7,D:D,$J$1) -> 0 | K7: =COUNTIFS(E:E, I7,D:D,$K$1) -> 0 | L7: =COUNTIFS(E:E, I7,D:D,$L$1) -> 1 | M7: =COUNTIFS(E:E, I7,D:D,$M$1) -> 1 | N7: =COUNTIFS(E:E, I7,D:D,$N$1) -> 0 | O7: =COUNTIFS(E:E, I7,D:D,$O$1) -> 1 | P7: =COUNTIFS(E:E, I7,D:D,$P$1) -> 0 | Q7: =COUNTIFS(E:E, I7,D:D,$Q$1) -> 0 | R7: =COUNTIFS(E:E, I7,D:D,$R$1) -> 3 | S7: 0
A8: P07 | B8: AppCivist: a service-oriented software platform for socially sustainable activism | C8: Animesh Pathak, Valerie Issarny, James Holston​ | D8: 2015 | E8: Proposal of Solution | F8: This paper proposes a solution for allowing social activism using service-oriented architecture. | H8: =SUM(J8:S8) -> 114 | J8: =SUM(J2:J7) -> 11 | K8: 7 | L8: =COUNTIFS(G:G, K8,F:F,$L$1) -> 0 | M8: 12 | N8: 6 | O8: 12 | P8: 11 | Q8: 17 | R8: 20 | S8: 18
A9: P08 | B9: SOA4DM: applying an SOA paradigm to coordination in humanitarian disaster response | C9: Kelly Lyons, Christie Oh | D9: 2015 | E9: Proposal of Solution | F9: This work provides an innovative approach for disaster management coordination, which is classified as a solution proposal.
A10: P09 | B10: Managing emergent ethical concerns for software engineering in society | C10: Awais Rashid, Karenza Moore, Corinne May-Chahal, Ruzanna Chitchyan | D10: 2015 | E10: Evaluation Research | F10: This evaluation research article focuses on addressing emerging ethical dilemmas in software engineering and presents iterative frameworks based on real-world projects.
A11: P10 | B11: Dementia and social sustainability: challenges for software engineering | C11: Alistair Sutcliffe, Paul Rayson, Chris Bull, Pete Sawyer | D11: 2015 | E11: Opinion Paper | F11: This is an opinion piece that discusses the junction of dementia care and software engineering.
A12: P11 | B12: Cognitively sustainable ICT with ubiquitous mobile services: challenges and opportunities | C12: Marcus Jägemar, Gordana Dodig Crnkovic​ | D12: 2015 | E12: Philosophical Paper | F12: Discusses difficulties and provides new frameworks for sustainable ICT; classified as a philosophical article.
A13: P12 | B13: Software energy profiling: comparing releases of a software product | C13: Erik A. Jagroep, Jan Martijn van der Werf, Giuseppe Procaccianti, Patricia Lago, Sjaak Brinkkemper, Leen Blom, Rob van Vliet | D13: 2016 | E13: Validation Research | F13: Examines the properties of a suggested solution and classifies it as validation research.
A14: P13 | B14: Sustainability design in requirements engineering: state of practice | C14: Ruzanna Chitchyan, Walter Cazzola, Awais Rashid | D14: 2016 | E14: Evaluation Research | F14: This study evaluates current sustainable design approaches in requirements engineering, making it an assessment research work.
A15: P14 | B15: Sustainability debt: a portfolio-based approach for evaluating sustainability requirements in architectures | C15: Javier Garbajosa, José Ángel Sanz, Mikael Svahnberg, Jan Bosch | D15: 2016 | E15: Proposal of Solution | F15: Offers a solution for evaluating sustainability requirements, hence proposing a solution.
A16: P15 | B16: Values-first SE: research principles in practice | C16: Maria Paasivaara, Casper Lassenius, Steven Fraser, Jürgen Münch, Kari Systä | D16: 2016 | E16: Philosophical Paper | F16: This paper is a philosophical study that examines the role of values in software engineering.
A17: P16 | B17: A guided tour of the legal implications of software cloning | C17: Paolo Ciancarini, Daniel Russo, Alberto Sillitti, Giancarlo Succi | D17: 2016 | E17: Philosophical Paper | F17: Discusses legal implications and frameworks, which fall under the area of philosophical papers.
A18: P17 | B18: Engineering software assemblies for participatory democracy: the participatory budgeting use case | C18: James Holston, Valérie Issarny, Cristhian Parra | D18: 2016 | E18: Evaluation Research | F18: Evaluates a practical application of participatory democracy and classifies it as evaluation research.
A19: P18 | B19: Software engineering and policy | C19: Anthony Finkelstein | D19: 2016 | E19: Opinion Paper | F19: Provides thoughts on the role of software engineering in policy formulation, falling under the category of opinion paper.
A20: P19 | B20: Characterising Sustainability Requirements: A New Species Red Herring or Just an Odd Fish? | C20: Colin C. Venters, Norbert Seyff, Christoph Becker, Stefanie Betz, Ruzanna Chitchyan, Leticia Duboc, Dan McIntyre, Birgit Penzenstadler | D20: 2017 | E20: Evaluation Research | F20: Evaluates sustainable design methods in software architecture, which falls under the topic of evaluation research.
... A124: P123 | B124: What Can Requirements Engineering Do for Emerging System of Systems? Case of Smart Local Energy | C124: R. Chitchyan | D124: 2024 | E124: Evaluation Research | F124: case study

Sheet keywords_data
A1: ID | B1: TITLE | C1: AUTHORS | D1: YEAR | E1: KEYWORDS | F1: SOURCE
A2: P01 | B2: Sustainability Design and Software: The Karlskrona Manifesto | C2: Christoph Becker, Ruzanna Chitchyan, Leticia Duboc, Steve Easterbrook, Birgit Penzenstadler, Norbert Seyff, Colin C. Venters | D2: 2015 | E2: Sustainability, Cross-disciplinary Initiative, Current Practice and Future Steps, Karlskrona Manifesto for Sustainability Design ,Software Engineering | F2: No, Absract
A3: P02 | B3: Interdisciplinary Design Patterns for Socially Aware Computing | C3: Harun Baraki, Kurt Geihs, Christian Voigtmann, Axel Hoffmann, Romy Kniewel, Bjo ̈rn-Elmar Macek and Julia Zirfas | D3: 2015 | E3: Design Patterns, Interdisciplinary, Social Compatibility, User Acceptance, Legal Compliance | F3: No, Absract
A4: P03 | B4: The role of design thinking and physical prototyping in social software engineering | C4: Peter Newman, Maria Angela Ferrario, Will Simm, Stephen Forshaw, Adrian Friday, Jon Whittle | D4: 2015 | E4: Social Software Engineering, Agile Approach, Physical Design, Renewable Energy | F4: No, Absract
A5: P04 | B5: On the role of value sensitive concerns in software engineering practice | C5: Balbir Barn, Ravinder Barn, Franco Raimondi​ | D5: 2015 | E5: Value Sensitive Design, Values, Co-Design, Requirements elicitation, Societal sustainability, Software engineering practice | F5: Yes, +Abstract
A6: P05 | B6: Engineering sustainability through language | C6: Ruzanna Chitchyan, Walter Cazzola, Awais Rashid​​ | D6: 2015 | E6: Sustainability, Programming Language, proof-of-concept, Micro-languages | F6: No, Absract
A7: P06 | B7: Enabling the definition and enforcement of governance rules in open source systems | C7: Javier Luis Cánovas Izquierdo, Jordi Cabot | D7: 2015 | E7: Governance Rules, Long-term Sustainability, Open Source Software (OSS), Mylyn | F7: No, Absract
A8: P07 | B8: AppCivist: a service-oriented software platform for socially sustainable activism | C8: Animesh Pathak, Valerie Issarny, James Holston​ | D8: 2015 | E8: ICT, Social Activism, Mobile Devices and Social Networking, Software Architectures, Interdisciplinary Research | F8: No, Absract
A9: P08 | B9: SOA4DM: applying an SOA paradigm to coordination in humanitarian disaster response | C9: Kelly Lyons, Christie Oh | D9: 2015 | E9: Service-Oriented Architecture (SOA), Disaster response, Crisis management, Resource management, Ethical Concerns | F9: Yes, +Abstract
A10: P09 | B10: Managing emergent ethical concerns for software engineering in society | C10: Awais Rashid, Karenza Moore, Corinne May-Chahal, Ruzanna Chitchyan | D10: 2015 | E10: Software Engineering, Ethics, Framework, Social Responsibility, Iterative Process | F10: No, Absract
A11: P10 | B11: Dementia and social sustainability: challenges for software engineering | C11: Alistair Sutcliffe, Paul Rayson, Chris Bull, Pete Sawyer | D11: 2015 | E11: Dementia, Software Engineering, Social Sustainability, Tailored Solutions, Quality of Life | F11: Yes, +Abstract
A12: P11 | B12: Cognitively sustainable ICT with ubiquitous mobile services: challenges and opportunities | C12: Marcus Jägemar, Gordana Dodig Crnkovic​ | D12: 2015 | E12: Cognitive sustainability, Social sustainability, Sustainable ICT, Cognitive revolution, Privacy, Shared attention, Social cognition, Software engineering for social good | F12: Yes
A13: P12 | B13: Software energy profiling: comparing releases of a software product | C13: Erik A. Jagroep, Jan Martijn van der Werf, Giuseppe Procaccianti, Patricia Lago, Sjaak Brinkkemper, Leen Blom, Rob van Vliet | D13: 2016 | E13: Energy Efficiency, Profiling, Software Architecture, Software, ICT Product, Experimentation, Measurement, Performance | F13: Yes, +Abstract
... A124: P123 | B124: What Can Requirements Engineering Do for Emerging System of Systems? Case of Smart Local Energy | C124: R. Chitchyan | D124: 2024 | E124: System-of-systems,Requirements engineering,case study,smart energy system,virtual system-of-systems,systems transition,energy transition | F124: Yes

Sheet keyword_id_mapping
A1: ID | B1: KEYWORDS
A2: P01 | B2: sustainability, cross-disciplinary initiative, current practice and future steps, karlskrona manifesto for sustainability design ,software engineering
A3: P02 | B3: design patterns, interdisciplinary, social compatibility, user acceptance, legal compliance
A4: P03 | B4: social software engineering, agile approach, physical design, renewable energy
A5: P04 | B5: value sensitive design, values, co-design, requirements elicitation, societal sustainability, software engineering practice
A6: P05 | B6: sustainability, programming language, proof-of-concept, micro-languages
A7: P06 | B7: governance rules, long-term sustainability, open source software (oss), mylyn
A8: P07 | B8: ict, social activism, mobile devices and social networking, software architectures, interdisciplinary research
A9: P08 | B9: service-oriented architecture (soa), disaster response, crisis management, resource management, ethical concerns
A10: P09 | B10: software engineering, ethics, framework, social responsibility, iterative process
A11: P10 | B11: dementia, software engineering, social sustainability, tailored solutions, quality of life
A12: P11 | B12: cognitive sustainability, social sustainability, sustainable ict, cognitive revolution, privacy, shared attention, social cognition, software engineering for social good
... A124: P123 | B124: system-of-systems,requirements engineering,case study,smart energy system,virtual system-of-systems,systems transition,energy transition

Sheet keyword_clusters
A1: Cluster | B1: Keywords | C1: Unique IDs | D1: Unique ID Count | E1: Keyword Count
A2: 5 | B2: Software Engineering, Software engineering practice, Software Engineering, Software Engineering, software engineering, Software Engineering, Software engineering, Software engineering, Software Engineering, Software Engineering Processes, software engineering, Software engineering, Software engineering education, Software engineering, Software Engineering, Software engineering, Software engineering, Software Engineering, software engineering, Software Engineering, Software Engineering, software engineering, Software Engineering, Software Engineering, software engineering, software engineering | C2: P01, P04, P09, P10, P14, P18, P27, P33, P34, P43, P47, P54, P58, P59, P70, P71, P78, P88, P89, P97, P99, P100, P114, P115, P116, P122 | D2: 26 | E2: 26 | G2: Keyword Category | H2: Total Keywords | I2: Study IDs
A3: 33 | B3: Sustainability, Societal sustainability, Sustainability, Long-term Sustainability, Social Sustainability, Cognitive sustainability, Social sustainability, Sustainability, Sustainability Design, Sustainability, sustainability debt, Sustainability, Sustainability Requirement, Sustainability, Sustainability, sustainability, environmental sustainability | C3: P01, P04, P05, P06, P10, P11, P13, P14, P19, P45, P54, P116, P118 | D3: 13 | E3: 17 | G3: Sustainability | H3: 17 | I3: P01, P04, P05, P06, P10, P11, P13, P14, P19, P45, P54, P116, P118
A4: 45 | B4: Diversity, Diversity, Diversity, diversity, Diversity, diversity, Diversity, Diversity, Diversity Awareness, Gender Diversity, diversity, Diversity | C4: P71, P77, P81, P85, P88, P90, P91, P96, P104, P108, P111 | D4: 11 | E4: 12 | G4: Diversity | H4: 12 | I4: P71, P77, P81, P85, P88, P90, P91, P96, P104, P108, P111
A5: 100 | B5: Open Source Software (OSS), Open Source Software Engineering, Open Source Software, Free/Open Source Software (FOSS), Open-Source Software, Open-Source Software Analysis, Open source Software development, Open source software, Open Source Software, Open-source Software | C5: P06, P21, P28, P29, P44, P72, P81, P104 | D5: 8 | E5: 10 | G5: Open Source Software | H5: 10 | I5: P06, P21, P28, P29, P44, P72, P81, P104
A6: 35 | B6: System Development, Software Development History, Software development, Software development, Freelance software development, Software Development, software development, software development teams, software development, software development | C6: P19, P28, P60, P76, P87, P94, P100, P108, P112, P120 | D6: 10 | E6: 10 | G6: Software Development | H6: 10 | I6: P19, P28, P60, P76, P87, P94, P100, P108, P112, P120
A7: 7 | B7: Inclusion, Inclusion, inclusion, Inclusion, inclusion, Inclusion | C7: P71, P80, P90, P91, P108, P111 | D7: 6 | E7: 6 | G7: Inclusion | H7: 6 | I7: P71, P80, P90, P91, P108, P111
A8: 32 | B8: Empirical Study, Empirical Study, Empirical study, Empirical Study, Empirical Studies, Empirical Theory | C8: P40, P42, P54, P66, P75, P88 | D8: 6 | E8: 6 | G8: Empirical Study | H8: 6 | I8: P40, P42, P54, P66, P75, P88
A9: 20 | B9: Gender Balance, Gender, Gender, Gender Inequalities, gender stereotypes, gender | C9: P40, P71, P85, P88, P89, P120 | D9: 6 | E9: 6 | G9: Gender | H9: 6 | I9: P40, P71, P85, P88, P89, P120
A10: 8 | B10: Machine learning, Machine learning, MACHINE LEARNING, machine learning, machine learning | C10: P25, P68, P98, P112, P122 | D10: 5 | E10: 5
A11: 99 | B11: Case Study, Case Study, case study, Case Study, case study | C11: P53, P94, P100, P111, P123 | D11: 5 | E11: 5
A12: 87 | B12: Physical Design, decision-making, design decisions, Design, Architecture Design decisions | C12: P03, P14, P15, P45 | D12: 4 | E12: 5
A13: 47 | B13: User Feedback, Feedback Analysis, User Reviews, User Feedback, feedback | C13: P30, P63, P65, P92 | D13: 4 | E13: 5
A14: 13 | B14: Open Source, Open source, Open source, open source, Open Source | C14: P77, P84, P85, P86, P99 | D14: 5 | E14: 5
A15: 40 | B15: Privacy, Privacy Requirements, Privacy, Privacy, privacy | C15: P11, P20, P37, P63, P109 | D15: 5 | E15: 5
A16: 59 | B16: Software Architectures, Software Architecture, architecture, Software architecture, Software architecture | C16: P07, P12, P14, P45, P118 | D16: 5 | E16: 5
A17: 26 | B17: Community Smells, Community Smells, Community Smells, Community Smells, Community Smells | C17: P40, P56, P66, P75, P121 | D17: 5 | E17: 5
A18: 44 | B18: Twitter, Social Media, Facebook, Social media, Social network | C18: P25, P63, P68, P82 | D18: 4 | E18: 5
A19: 49 | B19: Covid19, COVID-19, COVID-19, Covid19 | C19: P62, P63, P83, P85 | D19: 4 | E19: 4
A20: 56 | B20: Trust, Trust, Human Trust, System Trust | C20: P41, P46 | D20: 2 | E20: 4
A21: 127 | B21: Requirements elicitation, Requirements Engineering, requirements engineering, Requirements engineering | C21: P04, P13, P52, P123 | D21: 4 | E21: 4
... A381: 379 | B381: game theory | C381: P39 | D381: 1 | E381: 1

Sheet topics_per_year
A1: ID | B1: Year | C1: ID | D1: Year | E1: ID | F1: Year | G1: ID | H1: Year | I1: ID | J1: Year | K1: ID | L1: Year | M1: ID | N1: Year
A2: Sustainability | B2: Sustainability | C2: Diversity and Inclusion | D2: Diversity and Inclusion | E2: Open Source | F2: Open Source | G2: Ethics | H2: Ethics | I2: Gender | J2: Gender | K2: Social Media | L2: Social Media | M2: Atypical Interaction Capabilities | N2: Atypical Interaction Capabilities | P2: Year | Q2: Sustainability | R2: Diversity and Inclusion | S2: Open Source | T2: Ethics | U2: Gender | V2: Social Media | W2: Atypical Interaction Capabilities
A3: P01 | B3: {=INDEX(primary_studies!D:D, MATCH(A3, primary_studies!A:A, 0))} -> 2015 | C3: P71 | D3: {=INDEX(primary_studies!D:D, MATCH(C3, primary_studies!A:A, 0))} -> 2022 | E3: P06 | F3: {=INDEX(primary_studies!D:D, MATCH(E3, primary_studies!A:A, 0))} -> 2015 | G3: P08 | H3: {=INDEX(primary_studies!D:D, MATCH(G3, primary_studies!A:A, 0))} -> 2015 | I3: P38 | J3: {=INDEX(primary_studies!D:D, MATCH(I3, primary_studies!A:A, 0))} -> 2018 | K3: P25 | L3: {=INDEX(primary_studies!D:D, MATCH(K3, primary_studies!A:A, 0))} -> 2017 | M3: P10 | N3: {=INDEX(primary_studies!D:D, MATCH(M3, primary_studies!A:A, 0))} -> 2015 | P3: 2015 | Q3: =COUNTIF(B:B, P3) -> 7 | S3: =COUNTIF(F:F, P3) -> 1 | T3: =COUNTIF(H:H, P3) -> 2 | W3: =COUNTIF(N:N, P3) -> 1
A4: P04 | B4: {=INDEX(primary_studies!D:D, MATCH(A4, primary_studies!A:A, 0))} -> 2015 | C4: P76 | D4: {=INDEX(primary_studies!D:D, MATCH(C4, primary_studies!A:A, 0))} -> 2022 | E4: P21 | F4: {=INDEX(primary_studies!D:D, MATCH(E4, primary_studies!A:A, 0))} -> 2017 | G4: P09 | H4: {=INDEX(primary_studies!D:D, MATCH(G4, primary_studies!A:A, 0))} -> 2015 | I4: P40 | J4: {=INDEX(primary_studies!D:D, MATCH(I4, primary_studies!A:A, 0))} -> 2019 | K4: P42 | L4: {=INDEX(primary_studies!D:D, MATCH(K4, primary_studies!A:A, 0))} -> 2019 | M4: P50 | N4: {=INDEX(primary_studies!D:D, MATCH(M4, primary_studies!A:A, 0))} -> 2020 | P4: 2016 | Q4: =COUNTIF(B:B, P4) -> 2
A5: P05 | B5: {=INDEX(primary_studies!D:D, MATCH(A5, primary_studies!A:A, 0))} -> 2015 | C5: P77 | D5: {=INDEX(primary_studies!D:D, MATCH(C5, primary_studies!A:A, 0))} -> 2022 | E5: P28 | F5: {=INDEX(primary_studies!D:D, MATCH(E5, primary_studies!A:A, 0))} -> 2018 | G5: P35 | H5: {=INDEX(primary_studies!D:D, MATCH(G5, primary_studies!A:A, 0))} -> 2018 | I5: P69 | J5: {=INDEX(primary_studies!D:D, MATCH(I5, primary_studies!A:A, 0))} -> 2022 | K5: P63 | L5: {=INDEX(primary_studies!D:D, MATCH(K5, primary_studies!A:A, 0))} -> 2021 | M5: P78 | N5: {=INDEX(primary_studies!D:D, MATCH(M5, primary_studies!A:A, 0))} -> 2022 | P5: 2017 | Q5: =COUNTIF(B:B, P5) -> 2 | S5: =COUNTIF(F:F, P5) -> 1 | V5: =COUNTIF(L:L, P5) -> 1
A6: P06 | B6: {=INDEX(primary_studies!D:D, MATCH(A6, primary_studies!A:A, 0))} -> 2015 | C6: P80 | D6: {=INDEX(primary_studies!D:D, MATCH(C6, primary_studies!A:A, 0))} -> 2022 | E6: P29 | F6: {=INDEX(primary_studies!D:D, MATCH(E6, primary_studies!A:A, 0))} -> 2018 | G6: P53 | H6: {=INDEX(primary_studies!D:D, MATCH(G6, primary_studies!A:A, 0))} -> 2020 | I6: P71 | J6: {=INDEX(primary_studies!D:D, MATCH(I6, primary_studies!A:A, 0))} -> 2022 | K6: P68 | L6: {=INDEX(primary_studies!D:D, MATCH(K6, primary_studies!A:A, 0))} -> 2021 | M6: P95 | N6: {=INDEX(primary_studies!D:D, MATCH(M6, primary_studies!A:A, 0))} -> 2023 | P6: 2018 | Q6: =COUNTIF(B:B, P6) -> 1 | S6: =COUNTIF(F:F, P6) -> 2 | T6: =COUNTIF(H:H, P6) -> 1 | U6: =COUNTIF(J:J, P6) -> 1
A7: P09 | B7: {=INDEX(primary_studies!D:D, MATCH(A7, primary_studies!A:A, 0))} -> 2015 | C7: P81 | D7: {=INDEX(primary_studies!D:D, MATCH(C7, primary_studies!A:A, 0))} -> 2022 | E7: P44 | F7: {=INDEX(primary_studies!D:D, MATCH(E7, primary_studies!A:A, 0))} -> 2019 | G7: P63 | H7: {=INDEX(primary_studies!D:D, MATCH(G7, primary_studies!A:A, 0))} -> 2021 | I7: P85 | J7: {=INDEX(primary_studies!D:D, MATCH(I7, primary_studies!A:A, 0))} -> 2022 | K7: P82 | L7: {=INDEX(primary_studies!D:D, MATCH(K7, primary_studies!A:A, 0))} -> 2022 | M7: P111 | N7: {=INDEX(primary_studies!D:D, MATCH(M7, primary_studies!A:A, 0))} -> 2024 | P7: 2019 | Q7: =COUNTIF(B:B, P7) -> 1 | S7: =COUNTIF(F:F, P7) -> 1 | U7: =COUNTIF(J:J, P7) -> 1 | V7: =COUNTIF(L:L, P7) -> 1
A8: P10 | B8: {=INDEX(primary_studies!D:D, MATCH(A8, primary_studies!A:A, 0))} -> 2015 | C8: P85 | D8: {=INDEX(primary_studies!D:D, MATCH(C8, primary_studies!A:A, 0))} -> 2022 | E8: P72 | F8: {=INDEX(primary_studies!D:D, MATCH(E8, primary_studies!A:A, 0))} -> 2022 | G8: P70 | H8: {=INDEX(primary_studies!D:D, MATCH(G8, primary_studies!A:A, 0))} -> 2022 | I8: P88 | J8: {=INDEX(primary_studies!D:D, MATCH(I8, primary_studies!A:A, 0))} -> 2023 | K8: P92 | L8: {=INDEX(primary_studies!D:D, MATCH(K8, primary_studies!A:A, 0))} -> 2023 | P8: 2020 | Q8: =COUNTIF(B:B, P8) -> 1 | T8: =COUNTIF(H:H, P8) -> 1 | W8: =COUNTIF(N:N, P8) -> 1
A9: P11 | B9: {=INDEX(primary_studies!D:D, MATCH(A9, primary_studies!A:A, 0))} -> 2015 | C9: P86 | D9: {=INDEX(primary_studies!D:D, MATCH(C9, primary_studies!A:A, 0))} -> 2023 | E9: P77 | F9: {=INDEX(primary_studies!D:D, MATCH(E9, primary_studies!A:A, 0))} -> 2022 | G9: P92 | H9: {=INDEX(primary_studies!D:D, MATCH(G9, primary_studies!A:A, 0))} -> 2023 | I9: P89 | J9: {=INDEX(primary_studies!D:D, MATCH(I9, primary_studies!A:A, 0))} -> 2023 | K9: P110 | L9: {=INDEX(primary_studies!D:D, MATCH(K9, primary_studies!A:A, 0))} -> 2024 | P9: 2021 | T9: =COUNTIF(H:H, P9) -> 1 | V9: =COUNTIF(L:L, P9) -> 2
A10: P13 | B10: {=INDEX(primary_studies!D:D, MATCH(A10, primary_studies!A:A, 0))} -> 2016 | C10: P88 | D10: {=INDEX(primary_studies!D:D, MATCH(C10, primary_studies!A:A, 0))} -> 2023 | E10: P81 | F10: {=INDEX(primary_studies!D:D, MATCH(E10, primary_studies!A:A, 0))} -> 2022 | G10: P97 | H10: {=INDEX(primary_studies!D:D, MATCH(G10, primary_studies!A:A, 0))} -> 2023 | I10: P90 | J10: {=INDEX(primary_studies!D:D, MATCH(I10, primary_studies!A:A, 0))} -> 2023 | K10: P114 | L10: {=INDEX(primary_studies!D:D, MATCH(K10, primary_studies!A:A, 0))} -> 2024 | P10: 2022 | R10: =COUNTIF(D:D, P10) -> 6 | S10: =COUNTIF(F:F, P10) -> 5 | T10: =COUNTIF(H:H, P10) -> 1 | U10: =COUNTIF(J:J, P10) -> 3 | V10: =COUNTIF(L:L, P10) -> 1 | W10: =COUNTIF(N:N, P10) -> 1
A11: P14 | B11: {=INDEX(primary_studies!D:D, MATCH(A11, primary_studies!A:A, 0))} -> 2016 | C11: P90 | D11: {=INDEX(primary_studies!D:D, MATCH(C11, primary_studies!A:A, 0))} -> 2023 | E11: P84 | F11: {=INDEX(primary_studies!D:D, MATCH(E11, primary_studies!A:A, 0))} -> 2022 | G11: P101 | H11: {=INDEX(primary_studies!D:D, MATCH(G11, primary_studies!A:A, 0))} -> 2023 | I11: P120 | J11: {=INDEX(primary_studies!D:D, MATCH(I11, primary_studies!A:A, 0))} -> 2024 | P11: 2023 | R11: =COUNTIF(D:D, P11) -> 8 | S11: =COUNTIF(F:F, P11) -> 3 | T11: =COUNTIF(H:H, P11) -> 3 | U11: =COUNTIF(J:J, P11) -> 3 | V11: =COUNTIF(L:L, P11) -> 1 | W11: =COUNTIF(N:N, P11) -> 1
A12: P19 | B12: {=INDEX(primary_studies!D:D, MATCH(A12, primary_studies!A:A, 0))} -> 2017 | C12: P91 | D12: {=INDEX(primary_studies!D:D, MATCH(C12, primary_studies!A:A, 0))} -> 2023 | E12: P85 | F12: {=INDEX(primary_studies!D:D, MATCH(E12, primary_studies!A:A, 0))} -> 2022 | G12: P106 | H12: {=INDEX(primary_studies!D:D, MATCH(G12, primary_studies!A:A, 0))} -> 2024 | P12: 2024 | Q12: =COUNTIF(B:B, P12) -> 3 | R12: =COUNTIF(D:D, P12) -> 2 | T12: =COUNTIF(H:H, P12) -> 1 | U12: =COUNTIF(J:J, P12) -> 1 | V12: =COUNTIF(L:L, P12) -> 2 | W12: =COUNTIF(N:N, P12) -> 1
A13: P21 | B13: {=INDEX(primary_studies!D:D, MATCH(A13, primary_studies!A:A, 0))} -> 2017 | C13: P96 | D13: {=INDEX(primary_studies!D:D, MATCH(C13, primary_studies!A:A, 0))} -> 2023 | E13: P86 | F13: {=INDEX(primary_studies!D:D, MATCH(E13, primary_studies!A:A, 0))} -> 2023
A14: P36 | B14: {=INDEX(primary_studies!D:D, MATCH(A14, primary_studies!A:A, 0))} -> 2018 | C14: P97 | D14: {=INDEX(primary_studies!D:D, MATCH(C14, primary_studies!A:A, 0))} -> 2023 | E14: P99 | F14: {=INDEX(primary_studies!D:D, MATCH(E14, primary_studies!A:A, 0))} -> 2023
A15: P45 | B15: {=INDEX(primary_studies!D:D, MATCH(A15, primary_studies!A:A, 0))} -> 2019 | C15: P103 | D15: {=INDEX(primary_studies!D:D, MATCH(C15, primary_studies!A:A, 0))} -> 2023 | E15: P104 | F15: {=INDEX(primary_studies!D:D, MATCH(E15, primary_studies!A:A, 0))} -> 2023
A16: P54 | B16: {=INDEX(primary_studies!D:D, MATCH(A16, primary_studies!A:A, 0))} -> 2020 | C16: P104 | D16: {=INDEX(primary_studies!D:D, MATCH(C16, primary_studies!A:A, 0))} -> 2023
A17: P107 | B17: {=INDEX(primary_studies!D:D, MATCH(A17, primary_studies!A:A, 0))} -> 2024 | C17: P108 | D17: {=INDEX(primary_studies!D:D, MATCH(C17, primary_studies!A:A, 0))} -> 2024
A18: P116 | B18: {=INDEX(primary_studies!D:D, MATCH(A18, primary_studies!A:A, 0))} -> 2024 | C18: P111 | D18: {=INDEX(primary_studies!D:D, MATCH(C18, primary_studies!A:A, 0))} -> 2024
A19: P118 | B19: {=INDEX(primary_studies!D:D, MATCH(A19, primary_studies!A:A, 0))} -> 2024

Sheet topics
A1: ID | B1: Category | C1: ID | D1: Keywords | F1: ID Count | G1: Keyword Count
A2: C1 | B2: Sustainability | C2: P01, P04, P05, P06, P09, P10, P11, P13, P14, P19, P21, P36, P45, P54, P107, P116, P118 | D2: sustainability, karlskrona manifesto for sustainability design, sustainability, long-term sustainability, cognitive sustainability, sustainability, sustainability design, sustainability, environmental, individual sustainability, sustainability, sustainability requirement, environmental science, environmental modelling, sustainability, sustainability, sustainability, environmental sustainability, sustainable ict, societal sustainability, social responsibility, social sustainability, social sustainability, sustainable software engineering, green software engineering, software sustainability, green ai, sustainability debt | E2: =IFERROR(__xludf.DUMMYFUNCTION("TEXTJOIN("", "", TRUE, UNIQUE(SPLIT(C2, "", ""))) "),"P01, P04, P05, P06, P09, P10, P11, P13, P14, P19, P21, P36, P45, P54, P107, P116, P118") -> P01, P04, P05, P06, P09, P10, P11, P13, P14, P19, P21, P36, P45, P54, P107, P116, P118 | F2: =IFERROR(__xludf.DUMMYFUNCTION("COUNTA(SPLIT(E2, "","")) "),17) -> 17 | G2: =IFERROR(__xludf.DUMMYFUNCTION("COUNTA(SPLIT(D2, "","")) "),28) -> 28
A3: C2 | B3: Diversity and Inclusion | C3: P71, P76, P77, P80, P81, P85, P86, P88, P90, P91, P96, P97, P103, P104, P108, P111 | D3: diversity, diverse end-users, diversity, diversity, diversity, diversity and inclusion, diversity, diversity, diversity, diversity, diversity awareness, adaptation, gender diversity, diversity, diversity, inclusion, inclusion, inclusion, inclusion, inclusive speech, inclusion, inclusion | E3: =IFERROR(__xludf.DUMMYFUNCTION("TEXTJOIN("", "", TRUE, UNIQUE(SPLIT(C3, "", ""))) "),"P71, P76, P77, P80, P81, P85, P86, P88, P90, P91, P96, P97, P103, P104, P108, P111") -> P71, P76, P77, P80, P81, P85, P86, P88, P90, P91, P96, P97, P103, P104, P108, P111 | F3: =IFERROR(__xludf.DUMMYFUNCTION("COUNTA(SPLIT(E3, "","")) "),16) -> 16 | G3: =IFERROR(__xludf.DUMMYFUNCTION("COUNTA(SPLIT(D3, "","")) "),22) -> 22
A4: C3 | B4: Research Methodology | C4: P15, P16, P40, P42, P53, P54, P55, P66, P75, P94, P96, P100, P111, P123 | D4: action research, case law analysis, case study, case study, participant studies, case study, case study, case study, empirical study, empirical study, empirical study, empirical study, empirical study, empirical studies, | E4: =IFERROR(__xludf.DUMMYFUNCTION("TEXTJOIN("", "", TRUE, UNIQUE(SPLIT(C4, "", ""))) "),"P15, P16, P40, P42, P53, P54, P55, P66, P75, P94, P96, P100, P111, P123") -> P15, P16, P40, P42, P53, P54, P55, P66, P75, P94, P96, P100, P111, P123 | F4: =IFERROR(__xludf.DUMMYFUNCTION("COUNTA(SPLIT(E4, "","")) "),14) -> 14 | G4: =IFERROR(__xludf.DUMMYFUNCTION("COUNTA(SPLIT(D4, "","")) "),15) -> 15
A5: C4 | B5: Open Source | C5: P06, P21, P28, P29, P44, P72, P77, P81, P84, P85, P86, P99, P104 | D5: open source software (oss), open source software engineering, open source software, free/open source software (foss), open-source software, open-source software analysis, open source software development, open source software, open source, open source software, open source, open source, open source, open science, open source, open-source software | E5: =IFERROR(__xludf.DUMMYFUNCTION("TEXTJOIN("", "", TRUE, UNIQUE(SPLIT(C5, "", ""))) "),"P06, P21, P28, P29, P44, P72, P77, P81, P84, P85, P86, P99, P104") -> P06, P21, P28, P29, P44, P72, P77, P81, P84, P85, P86, P99, P104 | F5: =IFERROR(__xludf.DUMMYFUNCTION("COUNTA(SPLIT(E5, "","")) "),13) -> 13 | G5: =IFERROR(__xludf.DUMMYFUNCTION("COUNTA(SPLIT(D5, "","")) "),16) -> 16
A6: C5 | B6: Ethics | C6: P08, P09, P35, P53, P63, P70, P92, P97, P101, P106 | D6: ethical concerns, ethics, principled morality, harmful micropolitics, ethics, whistleblowing, ethics, harmful terminology, socio-ethical policy, responsibility | E6: =IFERROR(__xludf.DUMMYFUNCTION("TEXTJOIN("", "", TRUE, UNIQUE(SPLIT(C6, "", ""))) "),"P08, P09, P35, P53, P63, P70, P92, P97, P101, P106") -> P08, P09, P35, P53, P63, P70, P92, P97, P101, P106 | F6: =IFERROR(__xludf.DUMMYFUNCTION("COUNTA(SPLIT(E6, "","")) "),10) -> 10 | G6: =IFERROR(__xludf.DUMMYFUNCTION("COUNTA(SPLIT(D6, "","")) "),10) -> 10
A7: C6 | B7: Gender | C7: P38, P40, P69, P71, P85, P88, P89, P90, P120 | D7: gender bias, men's orientations, gender stereotypes, gender balance, persona, gender, gender, gender inequalities, lgbtqia+, gender, female developers, women, women | E7: =IFERROR(__xludf.DUMMYFUNCTION("TEXTJOIN("","", TRUE, UNIQUE(SPLIT(C7, "",""))) "),"P38, P40, P69, P71, P85, P88, P89, P90, P120") -> P38, P40, P69, P71, P85, P88, P89, P90, P120 | F7: =IFERROR(__xludf.DUMMYFUNCTION("COUNTA(SPLIT(E7, "","")) "),9) -> 9 | G7: =IFERROR(__xludf.DUMMYFUNCTION("COUNTA(SPLIT(D7, "","")) "),13) -> 13
A8: C7 | B8: Social Media | C8: P25, P42, P63, P68, P82, P92, P110, P114 | D8: twitter, stack overflow, online forums, social media, advertising, facebook, social media, crowdsourcing, social network, reddit, online platforms, linkedin | E8: =IFERROR(__xludf.DUMMYFUNCTION("TEXTJOIN("", "", TRUE, UNIQUE(SPLIT(C8, "", ""))) "),"P25, P42, P63, P68, P82, P92, P110, P114") -> P25, P42, P63, P68, P82, P92, P110, P114 | F8: =IFERROR(__xludf.DUMMYFUNCTION("COUNTA(SPLIT(E8, "","")) "),8) -> 8 | G8: =IFERROR(__xludf.DUMMYFUNCTION("COUNTA(SPLIT(D8, "","")) "),12) -> 12
A9: C8 | B9: Education | C9: P24, P47, P49, P83, P89, P93, P102 | D9: school, whiteboard, education, individualism, education, computing education, continuing education, accessibility education, androgogy, digital literacy, primary school students | E9: =IFERROR(__xludf.DUMMYFUNCTION("TEXTJOIN("", "", TRUE, UNIQUE(SPLIT(C9, "", ""))) "),"P24, P47, P49, P83, P89, P93, P102") -> P24, P47, P49, P83, P89, P93, P102 | F9: =IFERROR(__xludf.DUMMYFUNCTION("COUNTA(SPLIT(E9, "","")) "),7) -> 7 | G9: =IFERROR(__xludf.DUMMYFUNCTION("COUNTA(SPLIT(D9, "","")) "),11) -> 11
A10: C9 | B10: Atypical Interaction Capabilities | C10: P50, P78, P111, P10, P95 | D10: intellectual disability, autism, adhd, dementia, cognitive impairment, neurodiversity | E10: =IFERROR(__xludf.DUMMYFUNCTION("TEXTJOIN("", "", TRUE, UNIQUE(SPLIT(C10, "", ""))) "),"P50, P78, P111, P10, P95") -> P50, P78, P111, P10, P95 | F10: =IFERROR(__xludf.DUMMYFUNCTION("COUNTA(SPLIT(E10, "","")) "),5) -> 5 | G10: =IFERROR(__xludf.DUMMYFUNCTION("COUNTA(SPLIT(D10, "","")) "),6) -> 6

Sheet sustainabilityprimary
A1: ID | B1: TITLE | C1: AUTHORS | D1: YEAR | F1: Social Sustainability | G1: Economic Sustainability | H1: Environmental Sustainability | I1: Technical Sustainability | J1: Social | K1: Economic | L1: Environmental | M1: Technical | N1: Focus of the contribution | O1: CITATIONS
A2: P01 | B2: Sustainability Design and Software: The Karlskrona Manifesto | C2: Christoph Becker, Ruzanna Chitchyan, Leticia Duboc, Steve Easterbrook, Birgit Penzenstadler, Norbert Seyff, Colin C. Venters | D2: 2015 | F2: Community and Social Interaction | G2: Cost Efficiency | H2: Energy Efficiency | I2: System Longevity | J2: =IF(ISTEXT(F2), 1, 0) -> 1 | N2: mindset | O2: =VLOOKUP(A2, citation_data!A:E, 6, FALSE) -> #REF!
A3: P02 | B3: Interdisciplinary Design Patterns for Socially Aware Computing | C3: Harun Baraki, Kurt Geihs, Christian Voigtmann, Axel Hoffmann, Romy Kniewel, Bjo ̈rn-Elmar Macek and Julia Zirfas | D3: 2015 | F3: User Trust and Privacy | G3: Cost Efficiency | I3: Reusability of Design Patterns | M3: =IF(ISTEXT(I3), 1, 0) -> 1 | N3: solutions | O3: =VLOOKUP(A3, citation_data!A:E, 6, FALSE) -> #REF!
A4: P03 | B4: The role of design thinking and physical prototyping in social software engineering | C4: Peter Newman, Maria Angela Ferrario, Will Simm, Stephen Forshaw, Adrian Friday, Jon Whittle | D4: 2015 | F4: Community Engagement | G4: Cost-Effective | H4: Renewable Energy Integration | I4: Scalability | J4: =IF(ISTEXT(F4), 1, 0) -> 1 | N4: skills | O4: =VLOOKUP(A4, citation_data!A:E, 6, FALSE) -> #REF!
A5: P04 | B5: On the role of value sensitive concerns in software engineering practice | C5: Balbir Barn, Ravinder Barn, Franco Raimondi​ | D5: 2015 | F5: Human Values | G5: Cost Efficiency | M5: 1 | N5: model | O5: =VLOOKUP(A5, citation_data!A:E, 6, FALSE) -> #REF!
A6: P05 | B6: Engineering sustainability through language | C6: Ruzanna Chitchyan, Walter Cazzola, Awais Rashid​​ | D6: 2015 | G6: Cost-Effective | H6: Energy Efficiency | I6: Longevity and Adaptability | M6: =IF(ISTEXT(I6), 1, 0) -> 1 | N6: programming language | O6: =VLOOKUP(A6, citation_data!A:E, 6, FALSE) -> #REF!
A7: P06 | B7: Enabling the definition and enforcement of governance rules in open source systems | C7: Javier Luis Cánovas Izquierdo, Jordi Cabot | D7: 2015 | F7: Community Engagement | G7: Cost-Effective | I7: Maintainable and Adaptable | M7: =IF(ISTEXT(I7), 1, 0) -> 1 | N7: SE process | O7: =VLOOKUP(A7, citation_data!A:E, 6, FALSE) -> #REF!
A8: P07 | B8: AppCivist: a service-oriented software platform for socially sustainable activism | C8: Animesh Pathak, Valerie Issarny, James Holston​ | D8: 2015 | F8: Community Engagement | G8: Cost-Effective | H8: Resource Efficiency | J8: =IF(ISTEXT(F8), 1, 0) -> 1 | N8: activism | O8: =VLOOKUP(A8, citation_data!A:E, 6, FALSE) -> #REF!
A9: P08 | B9: SOA4DM: applying an SOA paradigm to coordination in humanitarian disaster response | C9: Kelly Lyons, Christie Oh | D9: 2015 | F9: Improved Coordination | I9: Scalability and Flexibility | M9: =IF(ISTEXT(I9), 1, 0) -> 1 | N9: SOA | O9: =VLOOKUP(A9, citation_data!A:E, 6, FALSE) -> #REF!
A10: P09 | B10: Managing emergent ethical concerns for software engineering in society | C10: Awais Rashid, Karenza Moore, Corinne May-Chahal, Ruzanna Chitchyan | D10: 2015 | F10: Community Engagement | G10: Cost-Effective | I10: Iterative Ethical Framework | M10: =IF(ISTEXT(I10), 1, 0) -> 1 | N10: SE process | O10: =VLOOKUP(A10, citation_data!A:E, 6, FALSE) -> #REF!
A11: P10 | B11: Dementia and social sustainability: challenges for software engineering | C11: Alistair Sutcliffe, Paul Rayson, Chris Bull, Pete Sawyer | D11: 2015 | F11: Support for Social Communities(Dementia patients in this case) | G11: Reducing Healthcare Costs | I11: Long-term Use and Adaptation | M11: =IF(ISTEXT(I11), 1, 0) -> 1 | N11: SE challenges | O11: =VLOOKUP(A11, citation_data!A:E, 6, FALSE) -> #REF!
A12: P11 | B12: Cognitively sustainable ICT with ubiquitous mobile services: challenges and opportunities | C12: Marcus Jägemar, Gordana Dodig Crnkovic​ | D12: 2015 | F12: Privacy, Work-Life Balance | J12: =IF(ISTEXT(F12), 1, 0) -> 1 | N12: cognition | O12: =VLOOKUP(A12, citation_data!A:E, 6, FALSE) -> #REF!
A13: P12 | B13: Software energy profiling: comparing releases of a software product | C13: Erik A. Jagroep, Jan Martijn van der Werf, Giuseppe Procaccianti, Patricia Lago, Sjaak Brinkkemper, Leen Blom, Rob van Vliet | D13: 2016 | G13: Resource Efficiency | H13: Energy Efficiency | M13: 1 | N13: profiling method | O13: =VLOOKUP(A13, citation_data!A:E, 6, FALSE) -> #REF!
A14: P13 | B14: Sustainability design in requirements engineering: state of practice | C14: Ruzanna Chitchyan, Walter Cazzola, Awais Rashid | D14: 2016 | G14: Cost Considerations | H14: Resource Efficiency | J14: 1 | N14: skills and organisation priorities | O14: =VLOOKUP(A14, citation_data!A:E, 6, FALSE) -> #REF!
A15: P14 | B15: Sustainability debt: a portfolio-based approach for evaluating sustainability requirements in architectures | C15: Javier Garbajosa, José Ángel Sanz, Mikael Svahnberg, Jan Bosch | D15: 2016 | F15: Societal Contribution | G15: Cost-Effective | H15: Energy Efficiency | I15: Maintainability | M15: =IF(ISTEXT(I15), 1, 0) -> 1 | N15: estimation | O15: =VLOOKUP(A15, citation_data!A:E, 6, FALSE) -> #REF!
A16: P15 | B16: Values-first SE: research principles in practice | C16: Maria Paasivaara, Casper Lassenius, Steven Fraser, Jürgen Münch, Kari Systä | D16: 2016 | F16: Human Values | G16: Cost-Efficiency | I16: Maintainable and Adaptable | M16: =IF(ISTEXT(I16), 1, 0) -> 1 | N16: SE process | O16: =VLOOKUP(A16, citation_data!A:E, 6, FALSE) -> #REF!
A17: P16 | B17: A guided tour of the legal implications of software cloning | C17: Paolo Ciancarini, Daniel Russo, Alberto Sillitti, Giancarlo Succi | D17: 2016 | G17: Market Competition | J17: 1 | N17: law | O17: =VLOOKUP(A17, citation_data!A:E, 6, FALSE) -> #REF!
A18: P17 | B18: Engineering software assemblies for participatory democracy: the participatory budgeting use case | C18: James Holston, Valérie Issarny, Cristhian Parra | D18: 2016 | F18: Community Engagement | G18: effective use of resources by Participatory Budgeting | I18: Integration and Flexibility | M18: =IF(ISTEXT(I18), 1, 0) -> 1 | N18: SE (process + product) | O18: =VLOOKUP(A18, citation_data!A:E, 6, FALSE) -> #REF!
A19: P18 | B19: Software engineering and policy | C19: Anthony Finkelstein | D19: 2016 | F19: Health | G19: Economic Prosperity | H19: Energy Policy | M19: 1 | N19: embed policy in SE | O19: =VLOOKUP(A19, citation_data!A:E, 6, FALSE) -> #REF!
A20: P19 | B20: Characterising Sustainability Requirements: A New Species Red Herring or Just an Odd Fish? | C20: Colin C. Venters, Norbert Seyff, Christoph Becker, Stefanie Betz, Ruzanna Chitchyan, Leticia Duboc, Dan McIntyre, Birgit Penzenstadler | D20: 2017 | F20: Societal Impact | G20: Cost Efficiency | H20: Energy Efficiency | I20: Maintainability | M20: =IF(ISTEXT(I20), 1, 0) -> 1 | N20: SE (RE) | O20: =VLOOKUP(A20, citation_data!A:E, 6, FALSE) -> #REF!
A21: P20 | B21: Privacy Requirements: Present & Future | C21: Pauline Anthonysamy, Awais Rashid, Ruzanna Chitchyan | D21: 2017 | F21: Societal Impact | I21: Maintainability | M21: =IF(ISTEXT(I21), 1, 0) -> 1 | N21: SE (RE) and process | O21: =VLOOKUP(A21, citation_data!A:E, 6, FALSE) -> #REF!
A22: P21 | B22: Preparing Research Projects for Sustainable Software Engineering in Society | C22: Dominik Renzel, István Koren, Ralf Klamma, Matthias Jarke | D22: 2017 | F22: sustainable community | I22: Maintainability | M22: =IF(ISTEXT(I22), 1, 0) -> 1 | N22: SE process | O22: =VLOOKUP(A22, citation_data!A:E, 6, FALSE) -> #REF!
A23: P22 | B23: Understanding How Software Can Support the Needs of Family Caregivers for Patients with Severe Conditions | C23: Angela di Fiore, Francesco Ceschel, Francesca Fiore, Marcos Baez, Fabio Casati, Giampaolo Armellin | D23: 2017 | F23: Community Building | I23: Maintainability | M23: =IF(ISTEXT(I23), 1, 0) -> 1 | N23: SE | O23: =VLOOKUP(A23, citation_data!A:E, 6, FALSE) -> #REF!
A24: P23 | B24: Portinari: A Data Exploration Tool to Personalize Cervical Cancer Screening | C24: Sagar Sen, Manoel Horta Ribeiro, Raquel C. de Melo Minardi, Wagner Meira Jr., Mari Nygård | D24: 2017 | F24: Community Health | G24: Cost Efficiency | M24: 1 | N24: tool | O24: =VLOOKUP(A24, citation_data!A:E, 6, FALSE) -> #REF!
A25: P24 | B25: Deploying Large Scale School Census Hub: An Experience Report | C25: Andrew Kinai, Juliet Mutahi, Karumba Samuel, Komminist Weldemariam | D25: 2017 | F25: Community Building | G25: Cost Efficiency | I25: Maintainability | M25: =IF(ISTEXT(I25), 1, 0) -> 1 | N25: data collection | O25: =VLOOKUP(A25, citation_data!A:E, 6, FALSE) -> #REF!
A26: P25 | B26: Crowdsourced Exploration of Mobile App Features: A Case Study of the Fort McMurray Wildfire | C26: Maleknaz Nayebi, Rachel Quapp, Guenther Ruhe, Mahshid Marbouti, Frank Maurer | D26: 2017 | F26: Community Building | I26: continuously analyze and integrate | M26: =IF(ISTEXT(I26), 1, 0) -> 1 | N26: method/tool | O26: =VLOOKUP(A26, citation_data!A:E, 6, FALSE) -> #REF!
A27: P26 | B27: Leveraging the Service Bus Paradigm for Computer-Mediated Social Communication Interoperability | C27: Rafael Angarita, Nikolaos Georgantas, Cristhian Parra, James Holston, Valérie Issarny | D27: 2017 | F27: Community Building | M27: 1 | N27: middleware | O27: =VLOOKUP(A27, citation_data!A:E, 6, FALSE) -> #REF!
A28: P27 | B28: Awakening Awareness on Energy Consumption in Software Engineering | C28: Erik Jagroep, Jordy Broekman, Jan Martijn E.M. van der Werf, Sjaak Brinkkemper, Patricia Lago, Leen Blom, Rob van Vliet | D28: 2017 | G28: Cost Efficiency | H28: Energy Efficiency | I28: integration of energy consumption considerations into the software development lifecycle | L28: =IF(ISTEXT(H28), 1, 0) -> 1 | N28: environmental awareness | O28: =VLOOKUP(A28, citation_data!A:E, 6, FALSE) -> #REF!
A29: P28 | B29: Software Heritage: Why and How We Collect, Preserve and Share All the Software Source Code | C29: Roberto Di Cosmo | D29: 2018 | F29: Cultural Preservation | G29: Cost Efficiency | I29: Adaptability | M29: =IF(ISTEXT(I29), 1, 0) -> 1 | N29: platform | O29: =VLOOKUP(A29, citation_data!A:E, 6, FALSE) -> #REF!
A30: P29 | B30: The Role of Foundations in Open Source Projects | C30: Javier Luis Cánovas Izquierdo, Jordi Cabot | D30: 2018 | F30: Community Building | I30: Maintainability | J30: =IF(ISTEXT(F30), 1, 0) -> 1 | N30: role of foundations | O30: =VLOOKUP(A30, citation_data!A:E, 6, FALSE) -> #REF!
A31: P30 | B31: User Feedback in the App Store: A Cross-Cultural Study | C31: Emitza Guzman, Luís Oliveira, Yves Steiner, Laura C. Wagner, Martin Glinz | D31: 2018 | F31: Inclusivity | I31: Adaptability | J31: =IF(ISTEXT(F31), 1, 0) -> 1 | N31: user feedback | O31: =VLOOKUP(A31, citation_data!A:E, 6, FALSE) -> #REF!
A32: P31 | B32: Assistive Computing: A Human-Centered Approach to Developing Computing Support for Cognition | C32: Simon Harper, Sean Bechhofer, Carsten Maple, Colin P. Perera, Dave Green, Andy Brown | D32: 2018 | F32: User-Centered Design | G32: Resource Efficiency | I32: Maintainable and Adaptable | M32: =IF(ISTEXT(I32), 1, 0) -> 1 | N32: SE process | O32: =VLOOKUP(A32, citation_data!A:E, 6, FALSE) -> #REF!
A33: P32 | B33: Agile Development for Vulnerable Populations: Lessons Learned and Recommendations | C33: Marcos Baez, Fabio Casati | D33: 2018 | F33: Human Centered Design | G33: Cost of Errors(Cost Efficiency) | I33: Adaptability | M33: =IF(ISTEXT(I33), 1, 0) -> 1 | N33: SE process | O33: =VLOOKUP(A33, citation_data!A:E, 6, FALSE) -> #REF!
A34: P33 | B34: Digitalization of Swedish Government Agencies - A Perspective Through the Lens of a Software Development Census | C34: Markus Borg, omas Olsson, Ulrik Franke, Sa ̈ıd Assar | D34: 2018 | F34: Community Engagement | G34: Cost Efficiency | I34: Maintainability | M34: =IF(ISTEXT(I34), 1, 0) -> 1 | N34: SE process | O34: =VLOOKUP(A34, citation_data!A:E, 6, FALSE) -> #REF!
A35: P34 | B35: Contracting Agile Developments for Mission Critical Systems in the Public Sector | C35: Daniel Russo, Gerolamo Taccogna, Paolo Ciancarini, Angelo Messina, Giancarlo Succi | D35: 2018 | G35: Cost Efficiency | I35: Maintainability | M35: =IF(ISTEXT(I35), 1, 0) -> 1 | N35: SE process | O35: =VLOOKUP(A35, citation_data!A:E, 6, FALSE) -> #REF!
A36: P35 | B36: Resolving Ambiguities in Regulations: Towards Achieving the Kohlbergian Stage of Principled Morality | C36: Smita Ghaisas, Abhishek Sainani, Preethu Rose | D36: 2018 | F36: Fairness | G36: Cost Efficiency | I36: Automation and Deep Learning | M36: =IF(ISTEXT(I36), 1, 0) -> 1 | N36: policy embedding tool | O36: =VLOOKUP(A36, citation_data!A:E, 6, FALSE) -> #REF!
A37: P36 | B37: SE in ES: Opportunities for Software Engineering and Cloud Computing in Environmental Science | C37: W.A. Simm, F. Samreen, R. Bassett, M.A. Ferrario, G. Blair, J. Whittle, P.J. Young | D37: 2018 | F37: Accessibility | G37: Cost Efficiency | H37: resource efficiency | I37: Adaptability | M37: =IF(ISTEXT(I37), 1, 0) -> 1 | N37: cloud | O37: =VLOOKUP(A37, citation_data!A:E, 6, FALSE) -> #REF!
A38: P37 | B38: Towards a Unified Conceptual Model for Surveillance Theories: "We Shall Meet in the Place Where There is no Darkness" - 1984, George Orwell | C38: Balbir S. Barn, Ravinder Barn | D38: 2018 | F38: Privacy | I38: Adaptability | M38: =IF(ISTEXT(I38), 1, 0) -> 1 | N38: IS design | O38: =VLOOKUP(A38, citation_data!A:E, 6, FALSE) -> #REF!
A39: P38 | B39: Competence-Confidence Gap: A Threat to Female Developers' Contribution on GitHub | C39: Zhendong Wang, Yi Wang, David Redmiles | D39: 2018 | F39: addressing gender gaps | G39: Maximizing Impact and Growth | J39: =IF(ISTEXT(F39), 1, 0) -> 1 | N39: gender gap | O39: =VLOOKUP(A39, citation_data!A:E, 6, FALSE) -> #REF!
A40: P39 | B40: Digital Ecclesia: Towards an Online Direct-Democracy Framework | C40: Dionysis Athanasopoulos | D40: 2018 | F40: inclusivity | G40: Cost Efficiency | I40: Scalability and Flexibility | M40: =IF(ISTEXT(I40), 1, 0) -> 1 | N40: platform | O40: =VLOOKUP(A40, citation_data!A:E, 6, FALSE) -> #REF!
A41: P40 | B41: Gender Diversity and Women in Software Teams: How Do They Affect Community Smells? | C41: Gemma Catolino, Fabio Palomba, Damian A. Tamburri, Alexander Serebrenik, Filomena Ferrucci | D41: 2019 | F41: Inclusivity and Diversity | J41: =IF(ISTEXT(F41), 1, 0) -> 1 | N41: gender balance | O41: =VLOOKUP(A41, citation_data!A:E, 6, FALSE) -> #REF!
A42: P41 | B42: Trust Beyond Computation Alone: Human Aspects of Trust in Blockchain Technologies | C42: Barnaby Craggs, Awais Rashid | D42: 2019 | F42: User Trust | G42: Trust in the system and the developers can lead to increased user engagement and investment | M42: 1 | N42: guidelines for addresisng trust in BC | O42: =VLOOKUP(A42, citation_data!A:E, 6, FALSE) -> #REF!
A43: P42 | B43: An Anatomy of Security Conversations in Stack Overflow | C43: Tamara Lopez, Thein Tun, Arosha Bandara, Mark Levine, Bashar Nuseibeh, Helen Sharp​ | D43: 2019 | F43: Community Engagement | I43: Security | J43: =IF(ISTEXT(F43), 1, 0) -> 1 | N43: interaction "patterns" | O43: =VLOOKUP(A43, citation_data!A:E, 6, FALSE) -> #REF!
A44: P43 | B44: Software Engineering in Civic Tech A Case Study about Code for Ireland | C44: Antti Knutas, Victoria Palacin, Giovanni Maccani, Markus Helfert | D44: 2019 | F44: Community Engagement | H44: resource management(water) | M44: 1 | N44: SE process | O44: =VLOOKUP(A44, citation_data!A:E, 6, FALSE) -> #REF!
A45: P44 | B45: Beyond the Code Itself: How Programmers Really Look at Pull Requests | C45: Denae Ford, Mahnaz Behroozi, Alexander Serebrenik, Chris Parnin | D45: 2019 | F45: Inclusivity and Diversity | J45: =IF(ISTEXT(F45), 1, 0) -> 1 | N45: skills (gender infleunce on decision) | O45: =VLOOKUP(A45, citation_data!A:E, 6, FALSE) -> #REF!
A46: P45 | B46: Architecture Design Decision Maps for Software Sustainability | C46: Patricia Lago, Ivano Malavolta, Paris Avgeriou, Henry Muccini, Alexander Serebrenik, Damian Andrew Tamburri, Gianluca Reggio​ | D46: 2019 | F46: Generational Equity | G46: Economic Value | H46: Energy Efficiency,Reducing Carbon | I46: Long-term Use | M46: =IF(ISTEXT(I46), 1, 0) -> 1 | N46: design | O46: =VLOOKUP(A46, citation_data!A:E, 6, FALSE) -> #REF!
A47: P46 | B47: Building Trust in the Untrustable | C47: Emilia Cioroaica, Barbora Buhnova, Thomas Kuhn, Daniel Schneider | D47: 2020 | F47: Human Trust, System Trust, Psycological Narrative | I47: Trust, Safety critical system, smart software agents | M47: =IF(ISTEXT(I47), 1, 0) -> 1 | N47: framework | O47: =VLOOKUP(A47, citation_data!A:E, 6, FALSE) -> #REF!
A48: P47 | B48: Debugging Hiring: What Went Right and What Went Wrong in the Technical Interview Process | C48: Mahnaz (Mana) Behroozi, Shivani Shirolkar, Titus Barik, Chris Parnin | D48: 2020 | F48: Employment Issues | J48: =IF(ISTEXT(F48), 1, 0) -> 1 | N48: hiring SEers | O48: =VLOOKUP(A48, citation_data!A:E, 6, FALSE) -> #REF!
A49: P48 | B49: Deep Learning for Smart Sewer Systems: Assessing Nonfunctional Requirements | C49: Hemanth Gudaparthi, Reese Johnson, Harshitha Challa, Nan Niu | D49: 2020 | I49: Robustness, Resilience | M49: =IF(ISTEXT(I49), 1, 0) -> 1 | O49: =VLOOKUP(A49, citation_data!A:E, 6, FALSE) -> #REF!
A50: P49 | B50: Designing Edutainment Software for Digital Skills Nurturing of Preschoolers. A Method Proposal. | C50: Adriana-Mihaela Guran, Grigoreta Sofia Cojocar, Anamaria Moldovan | D50: 2020 | F50: user centered design | M50: 1 | N50: design method | O50: =VLOOKUP(A50, citation_data!A:E, 6, FALSE) -> #REF!
A51: P50 | B51: Developing Software for Motivating Individuals with Intellectual Disabilities to do Outdoor Physical Activity | C51: Juan C Torrado, Ida Wold, Letizia Jaccheri, Susanna Pelagatti, Stefano Chessa, Javier Gomez, Gunnar Hartvigsen, Henriette Michalsen | D51: 2020 | F51: intellectual disability ,adapted navigational assistance, easy-to- read text, visual communication | M51: 1 | N51: SW product | O51: =VLOOKUP(A51, citation_data!A:E, 6, FALSE) -> #REF!
A52: P51 | B52: From Abstract Specifications to Application Generation | C52: José Miguel Pérez-Álvarez, Adrian Mos | D52: 2020 | I52: application generation, maintenance | M52: =IF(ISTEXT(I52), 1, 0) -> 1 | N52: tools | O52: =VLOOKUP(A52, citation_data!A:E, 6, FALSE) -> #REF!
A53: P52 | B53: From RE Cares to SE Cares: Software Engineering for Social Good, One Venue at a Time | C53: Alex Dekhtyar, Jane Hayes, Jennifer Horkoff, Gunter Mussbacher, Irit Hadar, Meira Levy, Tingting Yu, Jared Payne, Barbara Paech, Kim Youngjoon, Jo Eunjung, Heo Seungbum, Kim Youngjoon, Kim Youngjoon, Kim Youngjoon | D53: 2020 | F53: collaboration, social good | J53: =IF(ISTEXT(F53), 1, 0) -> 1 | N53: SE / RE Cares events | O53: =VLOOKUP(A53, citation_data!A:E, 6, FALSE) -> #REF!
A54: P53 | B54: How layered reuse can support harmful micropolitics: SAP ERP in surgery planning | C54: Dzifa Ametowobla, Lutz Prechelt | D54: 2020 | F54: micopolitics | G54: cost, logistics | H54: reuse | I54: Layered reuse | M54: =IF(ISTEXT(I54), 1, 0) -> 1 | N54: ERP | O54: =VLOOKUP(A54, citation_data!A:E, 6, FALSE) -> #REF!
A55: P54 | B55: Human Behaviour Centered Design: Developing a Software System for Cultural Heritage | C55: Julie Dugdale, Mahyar Tourchi Moghaddam, Henry Muccini | D55: 2020 | F55: urban security, visitor comfort, toursism sustianability | M55: 1 | N55: crowd monitoring system | O55: =VLOOKUP(A55, citation_data!A:E, 6, FALSE) -> #REF!
A56: P55 | B56: Is Using Deep Learning Frameworks Free? Characterizing Technical Debt in Deep Learning Frameworks | C56: Jiakun Liu, Qiao Huang, Xin Xia, Emad Shihab, David Lo, Shanping Li | D56: 2020 | G56: maintenance cost | I56: technical debt | M56: =IF(ISTEXT(I56), 1, 0) -> 1 | N56: technical debt analysis | O56: =VLOOKUP(A56, citation_data!A:E, 6, FALSE) -> #REF!
A57: P56 | B57: Refactoring Community Smells in the Wild: The Practitioner’s Field Manual | C57: Gemma Catolino, Fabio Palomba, Damian Andrew Tamburri, Alexander Serebrenik, Filomena Ferrucci | D57: 2020 | F57: community smells | J57: =IF(ISTEXT(F57), 1, 0) -> 1 | N57: behavior in SE process | O57: =VLOOKUP(A57, citation_data!A:E, 6, FALSE) -> #REF!
A58: P57 | B58: Society-Oriented Applications Development: Investigating Users' Values from Bangladeshi Agriculture Mobile Applications | C58: Rifat Ara Shams, Waqar Hussain, Gillian Oliver, Harsha Perera, Arif Nurwidyantoro, Jon Whittle | D58: 2020 | F58: user values | M58: 1 | N58: RE | O58: =VLOOKUP(A58, citation_data!A:E, 6, FALSE) -> #REF!
A59: P58 | B59: Exploring the Role of Creativity in Software Engineering | C59: Wouter Groeneveld, Laurens Luyten, Joost Vennekens, Kris Aerts​​ | D59: 2021 | F59: Gender Inclusiveness | J59: =IF(ISTEXT(F59), 1, 0) -> 1 | N59: skills | O59: =VLOOKUP(A59, citation_data!A:E, 6, FALSE) -> #REF!
A60: P59 | B60: Awareness and Perception of Agile in Saudi Software Industry | C60: Fahad S Altuwaijri, Maria Angela Ferrario | D60: 2021 | F60: Ethical Values | J60: =IF(ISTEXT(F60), 1, 0) -> 1 | N60: perception | O60: =VLOOKUP(A60, citation_data!A:E, 6, FALSE) -> #REF!
A61: P60 | B61: Résumé-Driven Development: A Definition and Empirical Characterization | C61: Sourav Bhattacharya, Pallavi Sharma, Sachin Kumar | D61: 2021 | F61: Gender Inclusiveness | J61: =IF(ISTEXT(F61), 1, 0) -> 1 | N61: hiring | O61: =VLOOKUP(A61, citation_data!A:E, 6, FALSE) -> #REF!
A62: P61 | B62: A First Look at Human Values-Violation in App Reviews | C62: Humphrey O. Obie, Waqar Hussain, Xin Xia, John Grundy, Li Li, Burak Turhan, Jon Whittle, Mojtaba Shahin | D62: 2021 | F62: Community Engagement | M62: 1 | N62: requirements in SE | O62: =VLOOKUP(A62, citation_data!A:E, 6, FALSE) -> #REF!
A63: P62 | B63: Investigating the Potential Impact of Values on Requirements and Software Engineering | C63: Soo Ling Lim, M. Ali Babar, Ross Jeffery, Bjorn Decreus | D63: 2021 | F63: Community Enhancing | M63: 1 | N63: taxonomy | O63: =VLOOKUP(A63, citation_data!A:E, 6, FALSE) -> #REF!
A64: P63 | B64: COVID-19 vs Social Media Apps: Does Privacy Really Matter? | C64: J. A. Goguen, S. Marsh, J. Waterson, M. A. Ferrario, W. Simm, W. Hussain, T. Nabity-Grover, C. M. Cheung, J. B. Thatcher, N. Ahmed, R. A. Michelin, W. Xue, S. Ruj | D64: 2021 | F64: Public Safety | G64: Cost Efficiency | H64: Environmental Monitoring and Protection | M64: 1 | N64: app | O64: =VLOOKUP(A64, citation_data!A:E, 6, FALSE) -> #REF!
A65: P64 | B65: QFL: Data-Driven Feedback Loop to Manage Quality in Agile Development | C65: Lidia López, Antonin Ahbervé, Alessandra Bagnato, Xavier Franch​​ | D65: 2021 | F65: Improving Communication(through examine culture diff) | M65: 1 | N65: SE process | O65: =VLOOKUP(A65, citation_data!A:E, 6, FALSE) -> #REF!
A66: P65 | B66: Does Culture Matter? Impact of Individualism and Uncertainty Avoidance on App Reviews | C66: Tom K. Landauer, Sai T. Moturu, Yiwen Huang | D66: 2021 | F66: Inclusiveness and Diversity | I66: Compatibility | M66: =IF(ISTEXT(I66), 1, 0) -> 1 | N66: platforms | O66: =VLOOKUP(A66, citation_data!A:E, 6, FALSE) -> #REF!
A67: P66 | B67: Understanding Community Smells Variability: A Statistical Approach | C67: Davide Fucci, Rafael Sachez, David Shepherd, Nachiappan Nagappan | D67: 2021 | F67: Inclusiveness and Diversity | I67: Compatibility | J67: =IF(ISTEXT(F67), 1, 0) -> 1 | N67: culture in SE | O67: =VLOOKUP(A67, citation_data!A:E, 6, FALSE) -> #REF!
A68: P67 | B68: Understanding Emotions of Developer Community Towards Software Documentation | C68: Akhila Sri Manasa Venigalla, Sridhar Chimalakonda​ | D68: 2021 | F68: Accessibility, Inclusiveness | I68: Compatibility | J68: =IF(ISTEXT(F68), 1, 0) -> 1 | N68: culture in SE | O68: =VLOOKUP(A68, citation_data!A:E, 6, FALSE) -> #REF!
A69: P68 | B69: Image-Based Social Sensing: Combining AI and the Crowd to Mine Policy-Adherence Indicators from Twitter | C69: Omar Haggag, Sherif Haggag, John Grundy, Mohamed Abdelrazek | D69: 2021 | F69: Inclusiveness | I69: Compatibility | M69: =IF(ISTEXT(I69), 1, 0) -> 1 | N69: tool to detect policy adherence | O69: =VLOOKUP(A69, citation_data!A:E, 6, FALSE) -> #REF!
A70: P69 | B70: A New Approach Towards Ensuring Gender Inclusive SE Job Advertisements | C70: Bianca Trinkenreich, Ricardo Britto, Marco A. Gerosa, Igor Steinmacher | D70: 2022 | F70: Inclusion and Accessibility | J70: =IF(ISTEXT(F70), 1, 0) -> 1 | N70: hiring | O70: =VLOOKUP(A70, citation_data!A:E, 6, FALSE) -> #REF!
A71: P70 | B71: A Review of How Whistleblowing is Studied in Software Engineering, and the Implications for Research and Practice | C71: Lucy Hunt, Maria Angela Ferrario | D71: 2022 | F71: Inclusiveness | M71: 1 | N71: SE process | O71: =VLOOKUP(A71, citation_data!A:E, 6, FALSE) -> #REF!
A72: P71 | B72: An empirical investigation on the challenges faced by women in the software industry: A case study | C72: Alice Allen, Alexander A. Gorshenev, Timur M. Mukhametzyanov, Sarah Sharp, Alexander Serebrenik | D72: 2022 | F72: Inclusiveness | J72: =IF(ISTEXT(F72), 1, 0) -> 1 | N72: gender issues | O72: =VLOOKUP(A72, citation_data!A:E, 6, FALSE) -> #REF!
A73: P72 | B73: Attracting and retaining oss contributors with a maintainer dashboard | C73: Mariam Guizani, Thomas Zimmermann, Anita Sarma, Denae Ford | D73: 2022 | F73: Public Health(In order to face further crisis) | I73: Compatibility | M73: =IF(ISTEXT(I73), 1, 0) -> 1 | N73: dashboard | O73: =VLOOKUP(A73, citation_data!A:E, 6, FALSE) -> #REF!
A74: P73 | B74: Detecting interpersonal conflict in issues and code review: cross pollinating open-and closed-source approaches | C74: Yijun Yu, Arosha Bandara, Bashar Nuseibeh | D74: 2022 | F74: Community Building | M74: 1 | N74: classifiers | O74: =VLOOKUP(A74, citation_data!A:E, 6, FALSE) -> #REF!
A75: P74 | B75: DRESS-ML: A domain-specific language for modelling exceptional scenarios and self-adaptive behaviours for drone-based applications | C75: Lucas Alves, José Davi Pereira, Natália Aragão, Matheus Chagas, Paulo Henrique Maia | D75: 2022 | F75: Gender Diversity | M75: 1 | N75: DSL | O75: =VLOOKUP(A75, citation_data!A:E, 6, FALSE) -> #REF!
A76: P75 | B76: Good fences make good neighbours? on the impact of cultural and geographical dispersion on community smells | C76: Stefano Lambiase, Gemma Catolino, Damian A. Tamburri, Alexander Serebrenik, Fabio Palomba, Filomena Ferrucci | D76: 2022 | F76: Access and Equity | I76: long-term usability | J76: =IF(ISTEXT(F76), 1, 0) -> 1 | N76: community smells | O76: =VLOOKUP(A76, citation_data!A:E, 6, FALSE) -> #REF!
A77: P76 | B77: How are diverse end-user human-centric issues discussed on GitHub? | C77: H. K. Dam, B. T. R. Savarimuthu, D. Avery, A. Ghose | D77: 2022 | I77: Security | J77: 1 | N77: human-centric issues | O77: =VLOOKUP(A77, citation_data!A:E, 6, FALSE) -> #REF!
A78: P77 | B78: How to debug inclusivity bugs? a debugging process with information architecture | C78: Mariam Guizani, Igor Steinmacher, Jillian Emard, Abrar Fallatah, Margaret Burnett, Anita Sarma | D78: 2022 | F78: Gender Inequality | M78: 1 | N78: debugging process | O78: =VLOOKUP(A78, citation_data!A:E, 6, FALSE) -> #REF!
A79: P78 | B79: Impact of animated objects on autistic and non-autistic users | C79: Marco A. Gerosa, Bianca Trinkenreich, Igor Steinmacher | D79: 2022 | F79: Inclusivity and Diversity | J79: =IF(ISTEXT(F79), 1, 0) -> 1 | N79: impact analysis | O79: =VLOOKUP(A79, citation_data!A:E, 6, FALSE) -> #REF!
A80: P79 | B80: Lowering barriers to application development with cloud-native domain-specific functions | C80: José Miguel Pérez-Álvarez, Adrian Mos, Benjamin V. Hanrahan, Iyadunni J. Adenuga | D80: 2022 | F80: Access and Equity | M80: 1 | N80: approach | O80: =VLOOKUP(A80, citation_data!A:E, 6, FALSE) -> #REF!
A81: P80 | B81: Open Data Inclusion through Narrative Approaches | C81: Josephine Harringer, Eva-Lotta Sallnäs Pysander, Thomas Hellström | D81: 2022 | F81: Inclusivity and Diversity | M81: 1 | N81: approach | O81: =VLOOKUP(A81, citation_data!A:E, 6, FALSE) -> #REF!
A82: P81 | B82: Perceptions of the State of D&I and D&I Initiative in the ASF | C82: Mariam Guizani, Bianca Trinkenreich, Aileen Abril Castro-Guzman, Igor Steinmacher, Marco Gerosa, Anita Sarma | D82: 2022 | F82: Inclusiveness,Access and Equity | J82: =IF(ISTEXT(F82), 1, 0) -> 1 | N82: analysis | O82: =VLOOKUP(A82, citation_data!A:E, 6, FALSE) -> #REF!
A83: P82 | B83: Scratch as social network: topic modeling and sentiment analysis in scratch projects | C83: Isabella Graßl, Gordon Fraser | D83: 2022 | F83: Equity | J83: =IF(ISTEXT(F83), 1, 0) -> 1 | N83: analysis | O83: =VLOOKUP(A83, citation_data!A:E, 6, FALSE) -> #REF!
A84: P83 | B84: Software engineers' response to public crisis: lessons learnt from spontaneously building an informative COVID-19 dashboard | C84: Han Wang, Chao Wu, Chunyang Chen, Burak Turhan, Shiping Chen, Jon Whittle | D84: 2022 | F84: Access and Equity | M84: 1 | N84: SE process (dashboarding) | O84: =VLOOKUP(A84, citation_data!A:E, 6, FALSE) -> #REF!
A85: P84 | B85: Why do projects join the Apache Software Foundation? | C85: Marco A. Gerosa, Bianca Trinkenreich, Igor Steinmacher | D85: 2022 | F85: Access and Equity | J85: =IF(ISTEXT(F85), 1, 0) -> 1 | N85: analysis | O85: =VLOOKUP(A85, citation_data!A:E, 6, FALSE) -> #REF!
A86: P85 | B86: Worldwide gender differences in public code contributions: and how they have been affected by the covid-19 pandemic | C86: Davide Rossi, Stefano Zacchiroli | D86: 2022 | F86: Inclusivity and Diversity | J86: =IF(ISTEXT(F86), 1, 0) -> 1 | N86: analysis | O86: =VLOOKUP(A86, citation_data!A:E, 6, FALSE) -> #REF!
A87: P86 | B87: Designing for Cognitive Diversity: Improving the GitHub Experience for Newcomers | C87: Italo Santos, Joao Felipe Pimentel, Igor Wiese, Igor Steinmacher, Anita Sarma, Marco Aurelio Gerosa | D87: 2023 | F87: Diversity, User Experience, Self-efficacy | I87: Bugs | M87: =IF(ISTEXT(I87), 1, 0) -> 1 | N87: platform | O87: =VLOOKUP(A87, citation_data!A:E, 6, FALSE) -> #REF!
A88: P87 | B88: Security Thinking in Online Freelance Software Development | C88: Irum Rauf, Marian Petre, Thein Tun, Tamara Lopez, Bashar Nuseibeh | D88: 2023 | F88: Security Thinking | I88: Security | M88: =IF(ISTEXT(I88), 1, 0) -> 1 | N88: guidelines | O88: =VLOOKUP(A88, citation_data!A:E, 6, FALSE) -> #REF!
A89: P88 | B89: Fundamentalists, Integrationists, & Transformationists: An Empirical Theory of Men Software Engineers’ Orientations in Gender Inequalities | C89: Yi Wang, Kexin Zhao, Travis Green, Qinghua Lu | D89: 2023 | F89: gender, social congnition (belief, attitude, action) | J89: =IF(ISTEXT(F89), 1, 0) -> 1 | N89: analysis | O89: =VLOOKUP(A89, citation_data!A:E, 6, FALSE) -> #REF!
A90: P89 | B90: Draw a Software Engineer Test - An Investigation into Children’s Perceptions of Software Engineering Profession | C90: Letizia Jaccheri, Claudia Maria Cutrupi, Irene Zanardi | D90: 2023 | F90: gender balance | J90: =IF(ISTEXT(F90), 1, 0) -> 1 | N90: perceptions | O90: =VLOOKUP(A90, citation_data!A:E, 6, FALSE) -> #REF!
A91: P90 | B91: Benefits and Limitations of Remote Work to LGBTQIA+ Software Professionals | C91: Ronnie de Souza Santos, Cleyton Vanut Cordeiro de Magalhães, Paul Ralph | D91: 2023 | F91: remote work, visibility, security, isolation, invisibility, LGBTQIA+ | J91: =IF(ISTEXT(F91), 1, 0) -> 1 | N91: analysis | O91: =VLOOKUP(A91, citation_data!A:E, 6, FALSE) -> #REF!
A92: P91 | B92: Hackathons as Inclusive Spaces for Prototyping Software in Open Social Innovation with NGOs | C92: Kiev Gama, George Valenca, Candy Estelle Marques Laurendon, Ajo Nasidi Marques, Lu is Eduardo Ramos, Ravena Amaral, Clarissa Maria Dubeux Lopes Barros, Guilherme Xavier | D92: 2023 | F92: inclusivity, | M92: 1 | N92: SE process | O92: =VLOOKUP(A92, citation_data!A:E, 6, FALSE) -> #REF!
A93: P92 | B93: Along the Margins: Marginalized Communities’ Ethical Concerns about Social Platforms | C93: Lauren Olson, Emitzá Guzmán, Florian Kunneman | D93: 2023 | F93: marginalized communities, ethical concerns, privacy, misinformation, discrimination | I93: development practices | J93: =IF(ISTEXT(F93), 1, 0) -> 1 | N93: analysis | O93: =VLOOKUP(A93, citation_data!A:E, 6, FALSE) -> #REF!
A94: P93 | B94: Do Users Act Equitably? Understanding User Bias Through a Large In-person Study | C94: Yang Liu, Heather Moses, Mark Sternefeld, Samuel Malachowsky, Daniel E. Krutz | D94: 2023 | F94: inequity, software ethics, AI/ML bias | I94: AI?ML bias | J94: =IF(ISTEXT(F94), 1, 0) -> 1 | N94: analysis | O94: =VLOOKUP(A94, citation_data!A:E, 6, FALSE) -> #REF!
A95: P94 | B95: Developing Software for Low Socio-Economic End Users: Lessons Learned from A Case Study of Fisherfolk Communities in Bangladesh | C95: Tanjila Kanij, Misita Zhan, Md Khalid Hossain, Adnan Abdul-Mageed | D95: 2023 | F95: low socio-economic background, digital literacy, | I95: prototyping for tacit knowledge transfer | M95: =IF(ISTEXT(I95), 1, 0) -> 1 | N95: SE process | O95: =VLOOKUP(A95, citation_data!A:E, 6, FALSE) -> #REF!
A96: P95 | B96: Walking Down the Road to Independent Mobility: An Adaptive Route Training System for the Cognitively Impaired | C96: Konstantin Rink, Tristan Gruschka, Gudrun Dobslaw | D96: 2023 | F96: mobility training, inclusive design, conginitive impairments, | I96: inclusive design practices | M96: =IF(ISTEXT(I96), 1, 0) -> 1 | N96: training system | O96: =VLOOKUP(A96, citation_data!A:E, 6, FALSE) -> #REF!
A97: P96 | B97: Diversity Awareness in Software Engineering Participant Research | C97: Riya Dutta, Diego Elias Costa, Emad Shihab, Torsten Tajmel | D97: 2023 | F97: diversity | J97: 1 | N97: diversity awarenss model for SE studies | O97: =VLOOKUP(A97, citation_data!A:E, 6, FALSE) -> #REF!
A98: P97 | B98: Harmful Terms in Computing: Towards Widespread Detection and Correction | C98: Hana Winchester, Alicia E. Boyd, Brittany Johnson | D98: 2023 | F98: Community Enhancing | M98: 1 | N98: DB + tool | O98: =VLOOKUP(A98, citation_data!A:E, 6, FALSE) -> #REF!
A99: P98 | B99: Metamorphic Testing and Debugging of Tax Preparation Software | C99: Saeid Tizpaz-Niari, Verya Monjezi, Markus Wagner, Sam Darian, Kimberly Reed, Ashutosh Trivedi | D99: 2023 | F99: Access and Equity | G99: Cost Efficiency | I99: maintainability | M99: =IF(ISTEXT(I99), 1, 0) -> 1 | N99: testing | O99: =VLOOKUP(A99, citation_data!A:E, 6, FALSE) -> #REF!
A100: P99 | B100: Treat societally impactful scientific insights as open-source software artifacts | C100: Cynthia C. S. Liem, Andrew M. Demetriou | D100: 2023 | F100: Access and Equity | G100: efficient resource use | I100: long-term usability | J100: =IF(ISTEXT(F100), 1, 0) -> 1 | N100: scientific impact, analysis | O100: =VLOOKUP(A100, citation_data!A:E, 6, FALSE) -> #REF!
...

Sheet sustainability_enabled
B1: TITLE | C1: AUTHORS | D1: YEAR | F1: Social Sustainability | G1: Economic Sustainability | H1: Environmental Sustainability | I1: Technical Sustainability | J1: Social | K1: Economic | L1: Environmental | M1: Technical
A2: P01 | B2: Sustainability Design and Software: The Karlskrona Manifesto | C2: Christoph Becker, Ruzanna Chitchyan, Leticia Duboc, Steve Easterbrook, Birgit Penzenstadler, Norbert Seyff, Colin C. Venters | D2: 2015 | F2: Community and Social Interaction | G2: Cost Efficiency | H2: Energy Efficiency | I2: System Longevity | J2: =IF(ISTEXT(F2), 1, 0) -> 1 | K2: =IF(ISTEXT(G2), 1, 0) -> 1 | L2: =IF(ISTEXT(H2), 1, 0) -> 1 | M2: =IF(ISTEXT(I2), 1, 0) -> 1 | N2: =SUM(J2:M2) -> 4
A3: P02 | B3: Interdisciplinary Design Patterns for Socially Aware Computing | C3: Harun Baraki, Kurt Geihs, Christian Voigtmann, Axel Hoffmann, Romy Kniewel, Bjo ̈rn-Elmar Macek and Julia Zirfas | D3: 2015 | F3: User Trust and Privacy | G3: Cost Efficiency | I3: Reusability of Design Patterns | J3: =IF(ISTEXT(F3), 1, 0) -> 1 | K3: =IF(ISTEXT(G3), 1, 0) -> 1 | L3: =IF(ISTEXT(H3), 1, 0) -> 0 | M3: =IF(ISTEXT(I3), 1, 0) -> 1 | N3: =SUM(J3:M3) -> 3
A4: P03 | B4: The role of design thinking and physical prototyping in social software engineering | C4: Peter Newman, Maria Angela Ferrario, Will Simm, Stephen Forshaw, Adrian Friday, Jon Whittle | D4: 2015 | F4: Community Engagement | G4: Cost-Effective | H4: Renewable Energy Integration | I4: Scalability | J4: =IF(ISTEXT(F4), 1, 0) -> 1 | K4: =IF(ISTEXT(G4), 1, 0) -> 1 | L4: =IF(ISTEXT(H4), 1, 0) -> 1 | M4: =IF(ISTEXT(I4), 1, 0) -> 1 | N4: =SUM(J4:M4) -> 4
A5: P04 | B5: On the role of value sensitive concerns in software engineering practice | C5: Balbir Barn, Ravinder Barn, Franco Raimondi​ | D5: 2015 | F5: Human Values | G5: Cost Efficiency | J5: =IF(ISTEXT(F5), 1, 0) -> 1 | K5: =IF(ISTEXT(G5), 1, 0) -> 1 | L5: =IF(ISTEXT(H5), 1, 0) -> 0 | M5: =IF(ISTEXT(I5), 1, 0) -> 0 | N5: =SUM(J5:M5) -> 2
A6: P05 | B6: Engineering sustainability through language | C6: Ruzanna Chitchyan, Walter Cazzola, Awais Rashid​​ | D6: 2015 | G6: Cost-Effective | H6: Energy Efficiency | I6: Longevity and Adaptability | J6: =IF(ISTEXT(F6), 1, 0) -> 0 | K6: =IF(ISTEXT(G6), 1, 0) -> 1 | L6: =IF(ISTEXT(H6), 1, 0) -> 1 | M6: =IF(ISTEXT(I6), 1, 0) -> 1 | N6: =SUM(J6:M6) -> 3
A7: P06 | B7: Enabling the definition and enforcement of governance rules in open source systems | C7: Javier Luis Cánovas Izquierdo, Jordi Cabot | D7: 2015 | F7: Community Engagement | G7: Cost-Effective | I7: Maintainable and Adaptable | J7: =IF(ISTEXT(F7), 1, 0) -> 1 | K7: =IF(ISTEXT(G7), 1, 0) -> 1 | L7: =IF(ISTEXT(H7), 1, 0) -> 0 | M7: =IF(ISTEXT(I7), 1, 0) -> 1 | N7: =SUM(J7:M7) -> 3
A8: P07 | B8: AppCivist: a service-oriented software platform for socially sustainable activism | C8: Animesh Pathak, Valerie Issarny, James Holston​ | D8: 2015 | F8: Community Engagement | G8: Cost-Effective | H8: Resource Efficiency | J8: =IF(ISTEXT(F8), 1, 0) -> 1 | K8: =IF(ISTEXT(G8), 1, 0) -> 1 | L8: =IF(ISTEXT(H8), 1, 0) -> 1 | M8: =IF(ISTEXT(I8), 1, 0) -> 0 | N8: =SUM(J8:M8) -> 3
A9: P08 | B9: SOA4DM: applying an SOA paradigm to coordination in humanitarian disaster response | C9: Kelly Lyons, Christie Oh | D9: 2015 | F9: Improved Coordination | I9: Scalability and Flexibility | J9: =IF(ISTEXT(F9), 1, 0) -> 1 | K9: =IF(ISTEXT(G9), 1, 0) -> 0 | L9: =IF(ISTEXT(H9), 1, 0) -> 0 | M9: =IF(ISTEXT(I9), 1, 0) -> 1 | N9: =SUM(J9:M9) -> 2
A10: P09 | B10: Managing emergent ethical concerns for software engineering in society | C10: Awais Rashid, Karenza Moore, Corinne May-Chahal, Ruzanna Chitchyan | D10: 2015 | F10: Community Engagement | G10: Cost-Effective | I10: Iterative Ethical Framework | J10: =IF(ISTEXT(F10), 1, 0) -> 1 | K10: =IF(ISTEXT(G10), 1, 0) -> 1 | L10: =IF(ISTEXT(H10), 1, 0) -> 0 | M10: =IF(ISTEXT(I10), 1, 0) -> 1 | N10: =SUM(J10:M10) -> 3
A11: P10 | B11: Dementia and social sustainability: challenges for software engineering | C11: Alistair Sutcliffe, Paul Rayson, Chris Bull, Pete Sawyer | D11: 2015 | F11: Support for Social Communities(Dementia patients in this case) | G11: Reducing Healthcare Costs | I11: Long-term Use and Adaptation | J11: =IF(ISTEXT(F11), 1, 0) -> 1 | K11: =IF(ISTEXT(G11), 1, 0) -> 1 | L11: =IF(ISTEXT(H11), 1, 0) -> 0 | M11: =IF(ISTEXT(I11), 1, 0) -> 1 | N11: =SUM(J11:M11) -> 3
A12: P11 | B12: Cognitively sustainable ICT with ubiquitous mobile services: challenges and opportunities | C12: Marcus Jägemar, Gordana Dodig Crnkovic​ | D12: 2015 | F12: Privacy, Work-Life Balance | J12: =IF(ISTEXT(F12), 1, 0) -> 1 | K12: =IF(ISTEXT(G12), 1, 0) -> 0 | L12: =IF(ISTEXT(H12), 1, 0) -> 0 | M12: =IF(ISTEXT(I12), 1, 0) -> 0 | N12: =SUM(J12:M12) -> 1
A13: P12 | B13: Software energy profiling: comparing releases of a software product | C13: Erik A. Jagroep, Jan Martijn van der Werf, Giuseppe Procaccianti, Patricia Lago, Sjaak Brinkkemper, Leen Blom, Rob van Vliet | D13: 2016 | G13: Resource Efficiency | H13: Energy Efficiency | J13: =IF(ISTEXT(F13), 1, 0) -> 0 | K13: =IF(ISTEXT(G13), 1, 0) -> 1 | L13: =IF(ISTEXT(H13), 1, 0) -> 1 | M13: =IF(ISTEXT(I13), 1, 0) -> 0 | N13: =SUM(J13:M13) -> 2
A14: P13 | B14: Sustainability design in requirements engineering: state of practice | C14: Ruzanna Chitchyan, Walter Cazzola, Awais Rashid | D14: 2016 | G14: Cost Considerations | H14: Resource Efficiency, renewable energy sources | J14: =IF(ISTEXT(F14), 1, 0) -> 0 | K14: =IF(ISTEXT(G14), 1, 0) -> 1 | L14: =IF(ISTEXT(H14), 1, 0) -> 1 | M14: =IF(ISTEXT(I14), 1, 0) -> 0 | N14: =SUM(J14:M14) -> 2
A15: P14 | B15: Sustainability debt: a portfolio-based approach for evaluating sustainability requirements in architectures | C15: Javier Garbajosa, José Ángel Sanz, Mikael Svahnberg, Jan Bosch | D15: 2016 | F15: Societal Contribution | G15: Cost-Effective | H15: Energy Efficiency | I15: Maintainability | J15: =IF(ISTEXT(F15), 1, 0) -> 1 | K15: =IF(ISTEXT(G15), 1, 0) -> 1 | L15: =IF(ISTEXT(H15), 1, 0) -> 1 | M15: =IF(ISTEXT(I15), 1, 0) -> 1 | N15: =SUM(J15:M15) -> 4
A16: P15 | B16: Values-first SE: research principles in practice | C16: Maria Paasivaara, Casper Lassenius, Steven Fraser, Jürgen Münch, Kari Systä | D16: 2016 | F16: Human Values | G16: Cost-Efficiency | I16: Maintainable and Adaptable | J16: =IF(ISTEXT(F16), 1, 0) -> 1 | K16: =IF(ISTEXT(G16), 1, 0) -> 1 | L16: =IF(ISTEXT(H16), 1, 0) -> 0 | M16: =IF(ISTEXT(I16), 1, 0) -> 1 | N16: =SUM(J16:M16) -> 3
A17: P16 | B17: A guided tour of the legal implications of software cloning | C17: Paolo Ciancarini, Daniel Russo, Alberto Sillitti, Giancarlo Succi | D17: 2016 | G17: Market Competition | J17: =IF(ISTEXT(F17), 1, 0) -> 0 | K17: =IF(ISTEXT(G17), 1, 0) -> 1 | L17: =IF(ISTEXT(H17), 1, 0) -> 0 | M17: =IF(ISTEXT(I17), 1, 0) -> 0 | N17: =SUM(J17:M17) -> 1
A18: P17 | B18: Engineering software assemblies for participatory democracy: the participatory budgeting use case | C18: James Holston, Valérie Issarny, Cristhian Parra | D18: 2016 | F18: Community Engagement | G18: effective use of resources by Participatory Budgeting | I18: Integration and Flexibility | J18: =IF(ISTEXT(F18), 1, 0) -> 1 | K18: =IF(ISTEXT(G18), 1, 0) -> 1 | L18: =IF(ISTEXT(H18), 1, 0) -> 0 | M18: =IF(ISTEXT(I18), 1, 0) -> 1 | N18: =SUM(J18:M18) -> 3
A19: P18 | B19: Software engineering and policy | C19: Anthony Finkelstein | D19: 2016 | F19: Health | G19: Economic Prosperity | H19: Energy Policy | J19: =IF(ISTEXT(F19), 1, 0) -> 1 | K19: =IF(ISTEXT(G19), 1, 0) -> 1 | L19: =IF(ISTEXT(H19), 1, 0) -> 1 | M19: =IF(ISTEXT(I19), 1, 0) -> 0 | N19: =SUM(J19:M19) -> 3
A20: P19 | B20: Characterising Sustainability Requirements: A New Species Red Herring or Just an Odd Fish? | C20: Colin C. Venters, Norbert Seyff, Christoph Becker, Stefanie Betz, Ruzanna Chitchyan, Leticia Duboc, Dan McIntyre, Birgit Penzenstadler | D20: 2017 | F20: Societal Impact | G20: Cost Efficiency | H20: Energy Efficiency | I20: Maintainability | J20: =IF(ISTEXT(F20), 1, 0) -> 1 | K20: =IF(ISTEXT(G20), 1, 0) -> 1 | L20: =IF(ISTEXT(H20), 1, 0) -> 1 | M20: =IF(ISTEXT(I20), 1, 0) -> 1 | N20: =SUM(J20:M20) -> 4
A21: P20 | B21: Privacy Requirements: Present & Future | C21: Pauline Anthonysamy, Awais Rashid, Ruzanna Chitchyan | D21: 2017 | F21: privacy | I21: Maintainability | J21: =IF(ISTEXT(F21), 1, 0) -> 1 | K21: =IF(ISTEXT(G21), 1, 0) -> 0 | L21: =IF(ISTEXT(H21), 1, 0) -> 0 | M21: =IF(ISTEXT(I21), 1, 0) -> 1 | N21: =SUM(J21:M21) -> 2
A22: P21 | B22: Preparing Research Projects for Sustainable Software Engineering in Society | C22: Dominik Renzel, István Koren, Ralf Klamma, Matthias Jarke | D22: 2017 | F22: sustainable community | I22: Maintainability | J22: =IF(ISTEXT(F22), 1, 0) -> 1 | K22: =IF(ISTEXT(G22), 1, 0) -> 0 | L22: =IF(ISTEXT(H22), 1, 0) -> 0 | M22: =IF(ISTEXT(I22), 1, 0) -> 1 | N22: =SUM(J22:M22) -> 2
A23: P22 | B23: Understanding How Software Can Support the Needs of Family Caregivers for Patients with Severe Conditions | C23: Angela di Fiore, Francesco Ceschel, Francesca Fiore, Marcos Baez, Fabio Casati, Giampaolo Armellin | D23: 2017 | F23: Community Building | I23: Maintainability | J23: =IF(ISTEXT(F23), 1, 0) -> 1 | K23: =IF(ISTEXT(G23), 1, 0) -> 0 | L23: =IF(ISTEXT(H23), 1, 0) -> 0 | M23: =IF(ISTEXT(I23), 1, 0) -> 1 | N23: =SUM(J23:M23) -> 2
A24: P23 | B24: Portinari: A Data Exploration Tool to Personalize Cervical Cancer Screening | C24: Sagar Sen, Manoel Horta Ribeiro, Raquel C. de Melo Minardi, Wagner Meira Jr., Mari Nygård | D24: 2017 | F24: Community Health | G24: Cost Efficiency | J24: =IF(ISTEXT(F24), 1, 0) -> 1 | K24: =IF(ISTEXT(G24), 1, 0) -> 1 | L24: =IF(ISTEXT(H24), 1, 0) -> 0 | M24: =IF(ISTEXT(I24), 1, 0) -> 0 | N24: =SUM(J24:M24) -> 2
A25: P24 | B25: Deploying Large Scale School Census Hub: An Experience Report | C25: Andrew Kinai, Juliet Mutahi, Karumba Samuel, Komminist Weldemariam | D25: 2017 | F25: Community Building | G25: Cost Efficiency | I25: Maintainability | J25: =IF(ISTEXT(F25), 1, 0) -> 1 | K25: =IF(ISTEXT(G25), 1, 0) -> 1 | L25: =IF(ISTEXT(H25), 1, 0) -> 0 | M25: =IF(ISTEXT(I25), 1, 0) -> 1 | N25: =SUM(J25:M25) -> 3
A26: P25 | B26: Crowdsourced Exploration of Mobile App Features: A Case Study of the Fort McMurray Wildfire | C26: Maleknaz Nayebi, Rachel Quapp, Guenther Ruhe, Mahshid Marbouti, Frank Maurer | D26: 2017 | F26: Community Building | I26: continuously analyze and integrate | J26: =IF(ISTEXT(F26), 1, 0) -> 1 | K26: =IF(ISTEXT(G26), 1, 0) -> 0 | L26: =IF(ISTEXT(H26), 1, 0) -> 0 | M26: =IF(ISTEXT(I26), 1, 0) -> 1 | N26: =SUM(J26:M26) -> 2
A27: P26 | B27: Leveraging the Service Bus Paradigm for Computer-Mediated Social Communication Interoperability | C27: Rafael Angarita, Nikolaos Georgantas, Cristhian Parra, James Holston, Valérie Issarny | D27: 2017 | F27: Community Building | J27: =IF(ISTEXT(F27), 1, 0) -> 1 | K27: =IF(ISTEXT(G27), 1, 0) -> 0 | L27: =IF(ISTEXT(H27), 1, 0) -> 0 | M27: =IF(ISTEXT(I27), 1, 0) -> 0 | N27: =SUM(J27:M27) -> 1
A28: P27 | B28: Awakening Awareness on Energy Consumption in Software Engineering | C28: Erik Jagroep, Jordy Broekman, Jan Martijn E.M. van der Werf, Sjaak Brinkkemper, Patricia Lago, Leen Blom, Rob van Vliet | D28: 2017 | G28: Cost Efficiency | H28: Energy Efficiency | I28: integration of energy consumption considerations into the software development lifecycle | J28: =IF(ISTEXT(F28), 1, 0) -> 0 | K28: =IF(ISTEXT(G28), 1, 0) -> 1 | L28: =IF(ISTEXT(H28), 1, 0) -> 1 | M28: =IF(ISTEXT(I28), 1, 0) -> 1 | N28: =SUM(J28:M28) -> 3
A29: P28 | B29: Software Heritage: Why and How We Collect, Preserve and Share All the Software Source Code | C29: Roberto Di Cosmo | D29: 2018 | F29: Cultural Preservation | G29: Cost Efficiency | I29: Adaptability | J29: =IF(ISTEXT(F29), 1, 0) -> 1 | K29: =IF(ISTEXT(G29), 1, 0) -> 1 | L29: =IF(ISTEXT(H29), 1, 0) -> 0 | M29: =IF(ISTEXT(I29), 1, 0) -> 1 | N29: =SUM(J29:M29) -> 3
A30: P29 | B30: The Role of Foundations in Open Source Projects | C30: Javier Luis Cánovas Izquierdo, Jordi Cabot | D30: 2018 | F30: Community Building | I30: Maintainability | J30: =IF(ISTEXT(F30), 1, 0) -> 1 | K30: =IF(ISTEXT(G30), 1, 0) -> 0 | L30: =IF(ISTEXT(H30), 1, 0) -> 0 | M30: =IF(ISTEXT(I30), 1, 0) -> 1 | N30: =SUM(J30:M30) -> 2
A31: P30 | B31: User Feedback in the App Store: A Cross-Cultural Study | C31: Emitza Guzman, Luís Oliveira, Yves Steiner, Laura C. Wagner, Martin Glinz | D31: 2018 | F31: Inclusivity | I31: Adaptability | J31: =IF(ISTEXT(F31), 1, 0) -> 1 | K31: =IF(ISTEXT(G31), 1, 0) -> 0 | L31: =IF(ISTEXT(H31), 1, 0) -> 0 | M31: =IF(ISTEXT(I31), 1, 0) -> 1 | N31: =SUM(J31:M31) -> 2
A32: P31 | B32: Assistive Computing: A Human-Centered Approach to Developing Computing Support for Cognition | C32: Simon Harper, Sean Bechhofer, Carsten Maple, Colin P. Perera, Dave Green, Andy Brown | D32: 2018 | F32: User-Centered Design | G32: Resource Efficiency | I32: Maintainable and Adaptable | J32: =IF(ISTEXT(F32), 1, 0) -> 1 | K32: =IF(ISTEXT(G32), 1, 0) -> 1 | L32: =IF(ISTEXT(H32), 1, 0) -> 0 | M32: =IF(ISTEXT(I32), 1, 0) -> 1 | N32: =SUM(J32:M32) -> 3
A33: P32 | B33: Agile Development for Vulnerable Populations: Lessons Learned and Recommendations | C33: Marcos Baez, Fabio Casati | D33: 2018 | F33: Human Centered Design | G33: Cost of Errors(Cost Efficiency) | I33: Adaptability | J33: =IF(ISTEXT(F33), 1, 0) -> 1 | K33: =IF(ISTEXT(G33), 1, 0) -> 1 | L33: =IF(ISTEXT(H33), 1, 0) -> 0 | M33: =IF(ISTEXT(I33), 1, 0) -> 1 | N33: =SUM(J33:M33) -> 3
A34: P33 | B34: Digitalization of Swedish Government Agencies - A Perspective Through the Lens of a Software Development Census | C34: Markus Borg, omas Olsson, Ulrik Franke, Sa ̈ıd Assar | D34: 2018 | F34: Community Engagement | G34: Cost Efficiency | I34: Maintainability | J34: =IF(ISTEXT(F34), 1, 0) -> 1 | K34: =IF(ISTEXT(G34), 1, 0) -> 1 | L34: =IF(ISTEXT(H34), 1, 0) -> 0 | M34: =IF(ISTEXT(I34), 1, 0) -> 1 | N34: =SUM(J34:M34) -> 3
A35: P34 | B35: Contracting Agile Developments for Mission Critical Systems in the Public Sector | C35: Daniel Russo, Gerolamo Taccogna, Paolo Ciancarini, Angelo Messina, Giancarlo Succi | D35: 2018 | G35: Cost Efficiency | I35: Maintainability | J35: =IF(ISTEXT(F35), 1, 0) -> 0 | K35: =IF(ISTEXT(G35), 1, 0) -> 1 | L35: =IF(ISTEXT(H35), 1, 0) -> 0 | M35: =IF(ISTEXT(I35), 1, 0) -> 1 | N35: =SUM(J35:M35) -> 2
A36: P35 | B36: Resolving Ambiguities in Regulations: Towards Achieving the Kohlbergian Stage of Principled Morality | C36: Smita Ghaisas, Abhishek Sainani, Preethu Rose | D36: 2018 | F36: Fairness | G36: Cost Efficiency | I36: Automation and Deep Learning | J36: =IF(ISTEXT(F36), 1, 0) -> 1 | K36: =IF(ISTEXT(G36), 1, 0) -> 1 | L36: =IF(ISTEXT(H36), 1, 0) -> 0 | M36: =IF(ISTEXT(I36), 1, 0) -> 1 | N36: =SUM(J36:M36) -> 3
A37: P36 | B37: SE in ES: Opportunities for Software Engineering and Cloud Computing in Environmental Science | C37: W.A. Simm, F. Samreen, R. Bassett, M.A. Ferrario, G. Blair, J. Whittle, P.J. Young | D37: 2018 | F37: Accessibility | G37: Cost Efficiency | H37: resource efficiency | I37: Adaptability | J37: =IF(ISTEXT(F37), 1, 0) -> 1 | K37: =IF(ISTEXT(G37), 1, 0) -> 1 | L37: =IF(ISTEXT(H37), 1, 0) -> 1 | M37: =IF(ISTEXT(I37), 1, 0) -> 1 | N37: =SUM(J37:M37) -> 4
A38: P37 | B38: Towards a Unified Conceptual Model for Surveillance Theories: "We Shall Meet in the Place Where There is no Darkness" - 1984, George Orwell | C38: Balbir S. Barn, Ravinder Barn | D38: 2018 | F38: Privacy | I38: Adaptability | J38: =IF(ISTEXT(F38), 1, 0) -> 1 | K38: =IF(ISTEXT(G38), 1, 0) -> 0 | L38: =IF(ISTEXT(H38), 1, 0) -> 0 | M38: =IF(ISTEXT(I38), 1, 0) -> 1 | N38: =SUM(J38:M38) -> 2
A39: P38 | B39: Competence-Confidence Gap: A Threat to Female Developers' Contribution on GitHub | C39: Zhendong Wang, Yi Wang, David Redmiles | D39: 2018 | F39: addressing gender gaps | G39: Maximizing Impact and Growth | J39: =IF(ISTEXT(F39), 1, 0) -> 1 | K39: =IF(ISTEXT(G39), 1, 0) -> 1 | L39: =IF(ISTEXT(H39), 1, 0) -> 0 | M39: =IF(ISTEXT(I39), 1, 0) -> 0 | N39: =SUM(J39:M39) -> 2
A40: P39 | B40: Digital Ecclesia: Towards an Online Direct-Democracy Framework | C40: Dionysis Athanasopoulos | D40: 2018 | F40: inclusivity | G40: Cost Efficiency | I40: Scalability and Flexibility | J40: =IF(ISTEXT(F40), 1, 0) -> 1 | K40: =IF(ISTEXT(G40), 1, 0) -> 1 | L40: =IF(ISTEXT(H40), 1, 0) -> 0 | M40: =IF(ISTEXT(I40), 1, 0) -> 1 | N40: =SUM(J40:M40) -> 3
A41: P40 | B41: Gender Diversity and Women in Software Teams: How Do They Affect Community Smells? | C41: Gemma Catolino, Fabio Palomba, Damian A. Tamburri, Alexander Serebrenik, Filomena Ferrucci | D41: 2019 | F41: Inclusivity and Diversity | J41: =IF(ISTEXT(F41), 1, 0) -> 1 | K41: =IF(ISTEXT(G41), 1, 0) -> 0 | L41: =IF(ISTEXT(H41), 1, 0) -> 0 | M41: =IF(ISTEXT(I41), 1, 0) -> 0 | N41: =SUM(J41:M41) -> 1
A42: P41 | B42: Trust Beyond Computation Alone: Human Aspects of Trust in Blockchain Technologies | C42: Barnaby Craggs, Awais Rashid | D42: 2019 | F42: User Trust | G42: Trust in the system and the developers can lead to increased user engagement and investment | J42: =IF(ISTEXT(F42), 1, 0) -> 1 | K42: =IF(ISTEXT(G42), 1, 0) -> 1 | L42: =IF(ISTEXT(H42), 1, 0) -> 0 | M42: =IF(ISTEXT(I42), 1, 0) -> 0 | N42: =SUM(J42:M42) -> 2
A43: P42 | B43: An Anatomy of Security Conversations in Stack Overflow | C43: Tamara Lopez, Thein Tun, Arosha Bandara, Mark Levine, Bashar Nuseibeh, Helen Sharp​ | D43: 2019 | F43: Community Engagement | I43: Security | J43: =IF(ISTEXT(F43), 1, 0) -> 1 | K43: =IF(ISTEXT(G43), 1, 0) -> 0 | L43: =IF(ISTEXT(H43), 1, 0) -> 0 | M43: =IF(ISTEXT(I43), 1, 0) -> 1 | N43: =SUM(J43:M43) -> 2
A44: P43 | B44: Software Engineering in Civic Tech A Case Study about Code for Ireland | C44: Antti Knutas, Victoria Palacin, Giovanni Maccani, Markus Helfert | D44: 2019 | F44: Community Engagement | H44: resource management(water) | J44: =IF(ISTEXT(F44), 1, 0) -> 1 | K44: =IF(ISTEXT(G44), 1, 0) -> 0 | L44: =IF(ISTEXT(H44), 1, 0) -> 1 | M44: =IF(ISTEXT(I44), 1, 0) -> 0 | N44: =SUM(J44:M44) -> 2
A45: P44 | B45: Beyond the Code Itself: How Programmers Really Look at Pull Requests | C45: Denae Ford, Mahnaz Behroozi, Alexander Serebrenik, Chris Parnin | D45: 2019 | F45: Inclusivity and Diversity | J45: =IF(ISTEXT(F45), 1, 0) -> 1 | K45: =IF(ISTEXT(G45), 1, 0) -> 0 | L45: =IF(ISTEXT(H45), 1, 0) -> 0 | M45: =IF(ISTEXT(I45), 1, 0) -> 0 | N45: =SUM(J45:M45) -> 1
A46: P45 | B46: Architecture Design Decision Maps for Software Sustainability | C46: Patricia Lago, Ivano Malavolta, Paris Avgeriou, Henry Muccini, Alexander Serebrenik, Damian Andrew Tamburri, Gianluca Reggio​ | D46: 2019 | F46: Generational Equity | G46: Economic Value | H46: Energy Efficiency,Reducing Carbon | I46: Long-term Use | J46: =IF(ISTEXT(F46), 1, 0) -> 1 | K46: =IF(ISTEXT(G46), 1, 0) -> 1 | L46: =IF(ISTEXT(H46), 1, 0) -> 1 | M46: =IF(ISTEXT(I46), 1, 0) -> 1 | N46: =SUM(J46:M46) -> 4
A47: P46 | B47: Building Trust in the Untrustable | C47: Emilia Cioroaica, Barbora Buhnova, Thomas Kuhn, Daniel Schneider | D47: 2020 | F47: Human Trust, System Trust, Psycological Narrative | I47: Trust, Safety critical system, smart software agents | J47: =IF(ISTEXT(F47), 1, 0) -> 1 | K47: =IF(ISTEXT(G47), 1, 0) -> 0 | L47: =IF(ISTEXT(H47), 1, 0) -> 0 | M47: =IF(ISTEXT(I47), 1, 0) -> 1 | N47: =SUM(J47:M47) -> 2
A48: P47 | B48: Debugging Hiring: What Went Right and What Went Wrong in the Technical Interview Process | C48: Mahnaz (Mana) Behroozi, Shivani Shirolkar, Titus Barik, Chris Parnin | D48: 2020 | F48: Employment Issues | J48: =IF(ISTEXT(F48), 1, 0) -> 1 | K48: =IF(ISTEXT(G48), 1, 0) -> 0 | L48: =IF(ISTEXT(H48), 1, 0) -> 0 | M48: =IF(ISTEXT(I48), 1, 0) -> 0 | N48: =SUM(J48:M48) -> 1
A49: P48 | B49: Deep Learning for Smart Sewer Systems: Assessing Nonfunctional Requirements | C49: Hemanth Gudaparthi, Reese Johnson, Harshitha Challa, Nan Niu | D49: 2020 | I49: Robustness, Resilience | J49: =IF(ISTEXT(F49), 1, 0) -> 0 | K49: =IF(ISTEXT(G49), 1, 0) -> 0 | L49: =IF(ISTEXT(H49), 1, 0) -> 0 | M49: =IF(ISTEXT(I49), 1, 0) -> 1 | N49: =SUM(J49:M49) -> 1
A50: P49 | B50: Designing Edutainment Software for Digital Skills Nurturing of Preschoolers. A Method Proposal. | C50: Adriana-Mihaela Guran, Grigoreta Sofia Cojocar, Anamaria Moldovan | D50: 2020 | F50: user centered design | J50: =IF(ISTEXT(F50), 1, 0) -> 1 | K50: =IF(ISTEXT(G50), 1, 0) -> 0 | L50: =IF(ISTEXT(H50), 1, 0) -> 0 | M50: =IF(ISTEXT(I50), 1, 0) -> 0 | N50: =SUM(J50:M50) -> 1
A51: P50 | B51: Developing Software for Motivating Individuals with Intellectual Disabilities to do Outdoor Physical Activity | C51: Juan C Torrado, Ida Wold, Letizia Jaccheri, Susanna Pelagatti, Stefano Chessa, Javier Gomez, Gunnar Hartvigsen, Henriette Michalsen | D51: 2020 | F51: intellectual disability ,adapted navigational assistance, easy-to- read text, visual communication | J51: =IF(ISTEXT(F51), 1, 0) -> 1 | K51: =IF(ISTEXT(G51), 1, 0) -> 0 | L51: =IF(ISTEXT(H51), 1, 0) -> 0 | M51: =IF(ISTEXT(I51), 1, 0) -> 0 | N51: =SUM(J51:M51) -> 1
A52: P51 | B52: From Abstract Specifications to Application Generation | C52: José Miguel Pérez-Álvarez, Adrian Mos | D52: 2020 | I52: application generation, maintenance | J52: =IF(ISTEXT(F52), 1, 0) -> 0 | K52: =IF(ISTEXT(G52), 1, 0) -> 0 | L52: =IF(ISTEXT(H52), 1, 0) -> 0 | M52: =IF(ISTEXT(I52), 1, 0) -> 1 | N52: =SUM(J52:M52) -> 1
A53: P52 | B53: From RE Cares to SE Cares: Software Engineering for Social Good, One Venue at a Time | C53: Alex Dekhtyar, Jane Hayes, Jennifer Horkoff, Gunter Mussbacher, Irit Hadar, Meira Levy, Tingting Yu, Jared Payne, Barbara Paech, Kim Youngjoon, Jo Eunjung, Heo Seungbum, Kim Youngjoon, Kim Youngjoon, Kim Youngjoon | D53: 2020 | F53: collaboration, social good | J53: =IF(ISTEXT(F53), 1, 0) -> 1 | K53: =IF(ISTEXT(G53), 1, 0) -> 0 | L53: =IF(ISTEXT(H53), 1, 0) -> 0 | M53: =IF(ISTEXT(I53), 1, 0) -> 0 | N53: =SUM(J53:M53) -> 1
A54: P53 | B54: How layered reuse can support harmful micropolitics: SAP ERP in surgery planning | C54: Dzifa Ametowobla, Lutz Prechelt | D54: 2020 | F54: micopolitics | G54: cost, logistics | I54: Layered reuse | J54: =IF(ISTEXT(F54), 1, 0) -> 1 | K54: =IF(ISTEXT(G54), 1, 0) -> 1 | L54: =IF(ISTEXT(H54), 1, 0) -> 0 | M54: =IF(ISTEXT(I54), 1, 0) -> 1 | N54: =SUM(J54:M54) -> 3
A55: P54 | B55: Human Behaviour Centered Design: Developing a Software System for Cultural Heritage | C55: Julie Dugdale, Mahyar Tourchi Moghaddam, Henry Muccini | D55: 2020 | F55: urban security, visitor comfort, toursism sustianability | J55: =IF(ISTEXT(F55), 1, 0) -> 1 | K55: =IF(ISTEXT(G55), 1, 0) -> 0 | L55: =IF(ISTEXT(H55), 1, 0) -> 0 | M55: =IF(ISTEXT(I55), 1, 0) -> 0 | N55: =SUM(J55:M55) -> 1
A56: P55 | B56: Is Using Deep Learning Frameworks Free? Characterizing Technical Debt in Deep Learning Frameworks | C56: Jiakun Liu, Qiao Huang, Xin Xia, Emad Shihab, David Lo, Shanping Li | D56: 2020 | G56: maintenance cost | I56: technical debt | J56: =IF(ISTEXT(F56), 1, 0) -> 0 | K56: =IF(ISTEXT(G56), 1, 0) -> 1 | L56: =IF(ISTEXT(H56), 1, 0) -> 0 | M56: =IF(ISTEXT(I56), 1, 0) -> 1 | N56: =SUM(J56:M56) -> 2
A57: P56 | B57: Refactoring Community Smells in the Wild: The Practitioner’s Field Manual | C57: Gemma Catolino, Fabio Palomba, Damian Andrew Tamburri, Alexander Serebrenik, Filomena Ferrucci | D57: 2020 | F57: community smells | J57: =IF(ISTEXT(F57), 1, 0) -> 1 | K57: =IF(ISTEXT(G57), 1, 0) -> 0 | L57: =IF(ISTEXT(H57), 1, 0) -> 0 | M57: =IF(ISTEXT(I57), 1, 0) -> 0 | N57: =SUM(J57:M57) -> 1
A58: P57 | B58: Society-Oriented Applications Development: Investigating Users' Values from Bangladeshi Agriculture Mobile Applications | C58: Rifat Ara Shams, Waqar Hussain, Gillian Oliver, Harsha Perera, Arif Nurwidyantoro, Jon Whittle | D58: 2020 | F58: user values | J58: =IF(ISTEXT(F58), 1, 0) -> 1 | K58: =IF(ISTEXT(G58), 1, 0) -> 0 | L58: =IF(ISTEXT(H58), 1, 0) -> 0 | M58: =IF(ISTEXT(I58), 1, 0) -> 0 | N58: =SUM(J58:M58) -> 1
A59: P58 | B59: Exploring the Role of Creativity in Software Engineering | C59: Wouter Groeneveld, Laurens Luyten, Joost Vennekens, Kris Aerts​​ | D59: 2021 | F59: Gender Inclusiveness | J59: =IF(ISTEXT(F59), 1, 0) -> 1 | K59: =IF(ISTEXT(G59), 1, 0) -> 0 | L59: =IF(ISTEXT(H59), 1, 0) -> 0 | M59: =IF(ISTEXT(I59), 1, 0) -> 0 | N59: =SUM(J59:M59) -> 1
A60: P59 | B60: Awareness and Perception of Agile in Saudi Software Industry | C60: Fahad S Altuwaijri, Maria Angela Ferrario | D60: 2021 | F60: Ethical Values | J60: =IF(ISTEXT(F60), 1, 0) -> 1 | K60: =IF(ISTEXT(G60), 1, 0) -> 0 | L60: =IF(ISTEXT(H60), 1, 0) -> 0 | M60: =IF(ISTEXT(I60), 1, 0) -> 0 | N60: =SUM(J60:M60) -> 1
A61: P60 | B61: Résumé-Driven Development: A Definition and Empirical Characterization | C61: Sourav Bhattacharya, Pallavi Sharma, Sachin Kumar | D61: 2021 | F61: Gender Inclusiveness | J61: =IF(ISTEXT(F61), 1, 0) -> 1 | K61: =IF(ISTEXT(G61), 1, 0) -> 0 | L61: =IF(ISTEXT(H61), 1, 0) -> 0 | M61: =IF(ISTEXT(I61), 1, 0) -> 0 | N61: =SUM(J61:M61) -> 1
A62: P61 | B62: A First Look at Human Values-Violation in App Reviews | C62: Humphrey O. Obie, Waqar Hussain, Xin Xia, John Grundy, Li Li, Burak Turhan, Jon Whittle, Mojtaba Shahin | D62: 2021 | F62: Community Engagement | J62: =IF(ISTEXT(F62), 1, 0) -> 1 | K62: =IF(ISTEXT(G62), 1, 0) -> 0 | L62: =IF(ISTEXT(H62), 1, 0) -> 0 | M62: =IF(ISTEXT(I62), 1, 0) -> 0 | N62: =SUM(J62:M62) -> 1
A63: P62 | B63: Investigating the Potential Impact of Values on Requirements and Software Engineering | C63: Soo Ling Lim, M. Ali Babar, Ross Jeffery, Bjorn Decreus | D63: 2021 | F63: Community Enhancing | J63: =IF(ISTEXT(F63), 1, 0) -> 1 | K63: =IF(ISTEXT(G63), 1, 0) -> 0 | L63: =IF(ISTEXT(H63), 1, 0) -> 0 | M63: =IF(ISTEXT(I63), 1, 0) -> 0 | N63: =SUM(J63:M63) -> 1
A64: P63 | B64: COVID-19 vs Social Media Apps: Does Privacy Really Matter? | C64: J. A. Goguen, S. Marsh, J. Waterson, M. A. Ferrario, W. Simm, W. Hussain, T. Nabity-Grover, C. M. Cheung, J. B. Thatcher, N. Ahmed, R. A. Michelin, W. Xue, S. Ruj | D64: 2021 | F64: Public Safety | G64: Cost Efficiency | H64: Environmental Monitoring and Protection | J64: =IF(ISTEXT(F64), 1, 0) -> 1 | K64: =IF(ISTEXT(G64), 1, 0) -> 1 | L64: =IF(ISTEXT(H64), 1, 0) -> 1 | M64: =IF(ISTEXT(I64), 1, 0) -> 0 | N64: =SUM(J64:M64) -> 3
A65: P64 | B65: QFL: Data-Driven Feedback Loop to Manage Quality in Agile Development | C65: Lidia López, Antonin Ahbervé, Alessandra Bagnato, Xavier Franch​​ | D65: 2021 | F65: Improving Communication(through examine culture diff) | J65: =IF(ISTEXT(F65), 1, 0) -> 1 | K65: =IF(ISTEXT(G65), 1, 0) -> 0 | L65: =IF(ISTEXT(H65), 1, 0) -> 0 | M65: =IF(ISTEXT(I65), 1, 0) -> 0 | N65: =SUM(J65:M65) -> 1
A66: P65 | B66: Does Culture Matter? Impact of Individualism and Uncertainty Avoidance on App Reviews | C66: Fischer, Ricarda Anna-Lena and Walczuch, Rita and Guzman, Emitza | D66: 2021 | F66: Inclusiveness and Diversity | I66: analysis of app reviews | J66: =IF(ISTEXT(F66), 1, 0) -> 1 | K66: =IF(ISTEXT(G66), 1, 0) -> 0 | L66: =IF(ISTEXT(H66), 1, 0) -> 0 | M66: =IF(ISTEXT(I66), 1, 0) -> 1 | N66: =SUM(J66:M66) -> 2
A67: P66 | B67: Understanding Community Smells Variability: A Statistical Approach | C67: Catolino, Gemma and Palomba, Fabio and Tamburri, Damian A. and Serebrenik, Alexander | D67: 2021 | F67: Inclusiveness and Diversity | I67: socio technical factors | J67: =IF(ISTEXT(F67), 1, 0) -> 1 | K67: =IF(ISTEXT(G67), 1, 0) -> 0 | L67: =IF(ISTEXT(H67), 1, 0) -> 0 | M67: =IF(ISTEXT(I67), 1, 0) -> 1 | N67: =SUM(J67:M67) -> 2
A68: P67 | B68: Understanding Emotions of Developer Community Towards Software Documentation | C68: Akhila Sri Manasa Venigalla, Sridhar Chimalakonda​ | D68: 2021 | F68: Accessibility, Inclusiveness | I68: Documentation | J68: =IF(ISTEXT(F68), 1, 0) -> 1 | K68: =IF(ISTEXT(G68), 1, 0) -> 0 | L68: =IF(ISTEXT(H68), 1, 0) -> 0 | M68: =IF(ISTEXT(I68), 1, 0) -> 1 | N68: =SUM(J68:M68) -> 2
A69: P68 | B69: Image-Based Social Sensing: Combining AI and the Crowd to Mine Policy-Adherence Indicators from Twitter | C69: Omar Haggag, Sherif Haggag, John Grundy, Mohamed Abdelrazek | D69: 2021 | F69: Inclusiveness | I69: image analysis | J69: =IF(ISTEXT(F69), 1, 0) -> 1 | K69: =IF(ISTEXT(G69), 1, 0) -> 0 | L69: =IF(ISTEXT(H69), 1, 0) -> 0 | M69: =IF(ISTEXT(I69), 1, 0) -> 1 | N69: =SUM(J69:M69) -> 2
A70: P69 | B70: A New Approach Towards Ensuring Gender Inclusive SE Job Advertisements | C70: Bianca Trinkenreich, Ricardo Britto, Marco A. Gerosa, Igor Steinmacher | D70: 2022 | F70: Inclusion and Accessibility | J70: =IF(ISTEXT(F70), 1, 0) -> 1 | K70: =IF(ISTEXT(G70), 1, 0) -> 0 | L70: =IF(ISTEXT(H70), 1, 0) -> 0 | M70: =IF(ISTEXT(I70), 1, 0) -> 0 | N70: =SUM(J70:M70) -> 1
A71: P70 | B71: A Review of How Whistleblowing is Studied in Software Engineering, and the Implications for Research and Practice | C71: Lucy Hunt, Maria Angela Ferrario | D71: 2022 | F71: Inclusiveness | J71: =IF(ISTEXT(F71), 1, 0) -> 1 | K71: =IF(ISTEXT(G71), 1, 0) -> 0 | L71: =IF(ISTEXT(H71), 1, 0) -> 0 | M71: =IF(ISTEXT(I71), 1, 0) -> 0 | N71: =SUM(J71:M71) -> 1
A72: P71 | B72: An empirical investigation on the challenges faced by women in the software industry: A case study | C72: Alice Allen, Alexander A. Gorshenev, Timur M. Mukhametzyanov, Sarah Sharp, Alexander Serebrenik | D72: 2022 | F72: Inclusiveness | J72: =IF(ISTEXT(F72), 1, 0) -> 1 | K72: =IF(ISTEXT(G72), 1, 0) -> 0 | L72: =IF(ISTEXT(H72), 1, 0) -> 0 | M72: =IF(ISTEXT(I72), 1, 0) -> 0 | N72: =SUM(J72:M72) -> 1
A73: P72 | B73: Attracting and retaining oss contributors with a maintainer dashboard | C73: Mariam Guizani, Thomas Zimmermann, Anita Sarma, Denae Ford | D73: 2022 | F73: Public Health(In order to face further crisis) | I73: Compatibility | J73: =IF(ISTEXT(F73), 1, 0) -> 1 | K73: =IF(ISTEXT(G73), 1, 0) -> 0 | L73: =IF(ISTEXT(H73), 1, 0) -> 0 | M73: =IF(ISTEXT(I73), 1, 0) -> 1 | N73: =SUM(J73:M73) -> 2
A74: P73 | B74: Detecting interpersonal conflict in issues and code review: cross pollinating open-and closed-source approaches | C74: Yijun Yu, Arosha Bandara, Bashar Nuseibeh | D74: 2022 | F74: Community Building | J74: =IF(ISTEXT(F74), 1, 0) -> 1 | K74: =IF(ISTEXT(G74), 1, 0) -> 0 | L74: =IF(ISTEXT(H74), 1, 0) -> 0 | M74: =IF(ISTEXT(I74), 1, 0) -> 0 | N74: =SUM(J74:M74) -> 1
A75: P74 | B75: DRESS-ML: A domain-specific language for modelling exceptional scenarios and self-adaptive behaviours for drone-based applications | C75: Lucas Alves, José Davi Pereira, Natália Aragão, Matheus Chagas, Paulo Henrique Maia | D75: 2022 | F75: Gender Diversity | J75: =IF(ISTEXT(F75), 1, 0) -> 1 | K75: =IF(ISTEXT(G75), 1, 0) -> 0 | L75: =IF(ISTEXT(H75), 1, 0) -> 0 | M75: =IF(ISTEXT(I75), 1, 0) -> 0 | N75: =SUM(J75:M75) -> 1
A76: P75 | B76: Good fences make good neighbours? on the impact of cultural and geographical dispersion on community smells | C76: Stefano Lambiase, Gemma Catolino, Damian A. Tamburri, Alexander Serebrenik, Fabio Palomba, Filomena Ferrucci | D76: 2022 | F76: Access and Equity | I76: long-term usability | J76: =IF(ISTEXT(F76), 1, 0) -> 1 | K76: =IF(ISTEXT(G76), 1, 0) -> 0 | L76: =IF(ISTEXT(H76), 1, 0) -> 0 | M76: =IF(ISTEXT(I76), 1, 0) -> 1 | N76: =SUM(J76:M76) -> 2
A77: P76 | B77: How are diverse end-user human-centric issues discussed on GitHub? | C77: H. K. Dam, B. T. R. Savarimuthu, D. Avery, A. Ghose | D77: 2022 | I77: Security | J77: =IF(ISTEXT(F77), 1, 0) -> 0 | K77: =IF(ISTEXT(G77), 1, 0) -> 0 | L77: =IF(ISTEXT(H77), 1, 0) -> 0 | M77: =IF(ISTEXT(I77), 1, 0) -> 1 | N77: =SUM(J77:M77) -> 1
A78: P77 | B78: How to debug inclusivity bugs? a debugging process with information architecture | C78: Mariam Guizani, Igor Steinmacher, Jillian Emard, Abrar Fallatah, Margaret Burnett, Anita Sarma | D78: 2022 | F78: Gender Inequality | J78: =IF(ISTEXT(F78), 1, 0) -> 1 | K78: =IF(ISTEXT(G78), 1, 0) -> 0 | L78: =IF(ISTEXT(H78), 1, 0) -> 0 | M78: =IF(ISTEXT(I78), 1, 0) -> 0 | N78: =SUM(J78:M78) -> 1
A79: P78 | B79: Impact of animated objects on autistic and non-autistic users | C79: Marco A. Gerosa, Bianca Trinkenreich, Igor Steinmacher | D79: 2022 | F79: Inclusivity and Diversity | J79: =IF(ISTEXT(F79), 1, 0) -> 1 | K79: =IF(ISTEXT(G79), 1, 0) -> 0 | L79: =IF(ISTEXT(H79), 1, 0) -> 0 | M79: =IF(ISTEXT(I79), 1, 0) -> 0 | N79: =SUM(J79:M79) -> 1
A80: P79 | B80: Lowering barriers to application development with cloud-native domain-specific functions | C80: José Miguel Pérez-Álvarez, Adrian Mos, Benjamin V. Hanrahan, Iyadunni J. Adenuga | D80: 2022 | F80: Access and Equity | J80: =IF(ISTEXT(F80), 1, 0) -> 1 | K80: =IF(ISTEXT(G80), 1, 0) -> 0 | L80: =IF(ISTEXT(H80), 1, 0) -> 0 | M80: =IF(ISTEXT(I80), 1, 0) -> 0 | N80: =SUM(J80:M80) -> 1
A81: P80 | B81: Open Data Inclusion through Narrative Approaches | C81: Josephine Harringer, Eva-Lotta Sallnäs Pysander, Thomas Hellström | D81: 2022 | F81: Inclusivity and Diversity | J81: =IF(ISTEXT(F81), 1, 0) -> 1 | K81: =IF(ISTEXT(G81), 1, 0) -> 0 | L81: =IF(ISTEXT(H81), 1, 0) -> 0 | M81: =IF(ISTEXT(I81), 1, 0) -> 0 | N81: =SUM(J81:M81) -> 1
A82: P81 | B82: Perceptions of the State of D&I and D&I Initiative in the ASF | C82: Mariam Guizani, Bianca Trinkenreich, Aileen Abril Castro-Guzman, Igor Steinmacher, Marco Gerosa, Anita Sarma | D82: 2022 | F82: Inclusiveness,Access and Equity | J82: =IF(ISTEXT(F82), 1, 0) -> 1 | K82: =IF(ISTEXT(G82), 1, 0) -> 0 | L82: =IF(ISTEXT(H82), 1, 0) -> 0 | M82: =IF(ISTEXT(I82), 1, 0) -> 0 | N82: =SUM(J82:M82) -> 1
A83: P82 | B83: Scratch as social network: topic modeling and sentiment analysis in scratch projects | C83: Isabella Graßl, Gordon Fraser | D83: 2022 | F83: Equity | J83: =IF(ISTEXT(F83), 1, 0) -> 1 | K83: =IF(ISTEXT(G83), 1, 0) -> 0 | L83: =IF(ISTEXT(H83), 1, 0) -> 0 | M83: =IF(ISTEXT(I83), 1, 0) -> 0 | N83: =SUM(J83:M83) -> 1
A84: P83 | B84: Software engineers' response to public crisis: lessons learnt from spontaneously building an informative COVID-19 dashboard | C84: Han Wang, Chao Wu, Chunyang Chen, Burak Turhan, Shiping Chen, Jon Whittle | D84: 2022 | F84: Access and Equity | J84: =IF(ISTEXT(F84), 1, 0) -> 1 | K84: =IF(ISTEXT(G84), 1, 0) -> 0 | L84: =IF(ISTEXT(H84), 1, 0) -> 0 | M84: =IF(ISTEXT(I84), 1, 0) -> 0 | N84: =SUM(J84:M84) -> 1
A85: P84 | B85: Why do projects join the Apache Software Foundation? | C85: Marco A. Gerosa, Bianca Trinkenreich, Igor Steinmacher | D85: 2022 | F85: Access and Equity | J85: =IF(ISTEXT(F85), 1, 0) -> 1 | K85: =IF(ISTEXT(G85), 1, 0) -> 0 | L85: =IF(ISTEXT(H85), 1, 0) -> 0 | M85: =IF(ISTEXT(I85), 1, 0) -> 0 | N85: =SUM(J85:M85) -> 1
A86: P85 | B86: Worldwide gender differences in public code contributions: and how they have been affected by the covid-19 pandemic | C86: Davide Rossi, Stefano Zacchiroli | D86: 2022 | F86: Inclusivity and Diversity | J86: =IF(ISTEXT(F86), 1, 0) -> 1 | K86: =IF(ISTEXT(G86), 1, 0) -> 0 | L86: =IF(ISTEXT(H86), 1, 0) -> 0 | M86: =IF(ISTEXT(I86), 1, 0) -> 0 | N86: =SUM(J86:M86) -> 1
A87: P86 | B87: Designing for Cognitive Diversity: Improving the GitHub Experience for Newcomers | C87: Italo Santos, Joao Felipe Pimentel, Igor Wiese, Igor Steinmacher, Anita Sarma, Marco Aurelio Gerosa | D87: 2023 | F87: Diversity, User Experience, Self-efficacy | I87: Bugs | J87: =IF(ISTEXT(F87), 1, 0) -> 1 | K87: =IF(ISTEXT(G87), 1, 0) -> 0 | L87: =IF(ISTEXT(H87), 1, 0) -> 0 | M87: =IF(ISTEXT(I87), 1, 0) -> 1 | N87: =SUM(J87:M87) -> 2
A88: P87 | B88: Security Thinking in Online Freelance Software Development | C88: Irum Rauf, Marian Petre, Thein Tun, Tamara Lopez, Bashar Nuseibeh | D88: 2023 | F88: Security Thinking | I88: Security | J88: =IF(ISTEXT(F88), 1, 0) -> 1 | K88: =IF(ISTEXT(G88), 1, 0) -> 0 | L88: =IF(ISTEXT(H88), 1, 0) -> 0 | M88: =IF(ISTEXT(I88), 1, 0) -> 1 | N88: =SUM(J88:M88) -> 2
A89: P88 | B89: Fundamentalists, Integrationists, & Transformationists: An Empirical Theory of Men Software Engineers’ Orientations in Gender Inequalities | C89: Yi Wang, Kexin Zhao, Travis Green, Qinghua Lu | D89: 2023 | F89: gender, social congnition (belief, attitude, action) | J89: =IF(ISTEXT(F89), 1, 0) -> 1 | K89: =IF(ISTEXT(G89), 1, 0) -> 0 | L89: =IF(ISTEXT(H89), 1, 0) -> 0 | M89: =IF(ISTEXT(I89), 1, 0) -> 0 | N89: =SUM(J89:M89) -> 1
A90: P89 | B90: Draw a Software Engineer Test - An Investigation into Children’s Perceptions of Software Engineering Profession | C90: Letizia Jaccheri, Claudia Maria Cutrupi, Irene Zanardi | D90: 2023 | F90: gender balance | J90: =IF(ISTEXT(F90), 1, 0) -> 1 | K90: =IF(ISTEXT(G90), 1, 0) -> 0 | L90: =IF(ISTEXT(H90), 1, 0) -> 0 | M90: =IF(ISTEXT(I90), 1, 0) -> 0 | N90: =SUM(J90:M90) -> 1
A91: P90 | B91: Benefits and Limitations of Remote Work to LGBTQIA+ Software Professionals | C91: Ronnie de Souza Santos, Cleyton Vanut Cordeiro de Magalhães, Paul Ralph | D91: 2023 | F91: remote work, visibility, security, isolation, invisibility, LGBTQIA+ | J91: =IF(ISTEXT(F91), 1, 0) -> 1 | K91: =IF(ISTEXT(G91), 1, 0) -> 0 | L91: =IF(ISTEXT(H91), 1, 0) -> 0 | M91: =IF(ISTEXT(I91), 1, 0) -> 0 | N91: =SUM(J91:M91) -> 1
A92: P91 | B92: Hackathons as Inclusive Spaces for Prototyping Software in Open Social Innovation with NGOs | C92: Kiev Gama, George Valenca, Candy Estelle Marques Laurendon, Ajo Nasidi Marques, Lu is Eduardo Ramos, Ravena Amaral, Clarissa Maria Dubeux Lopes Barros, Guilherme Xavier | D92: 2023 | F92: inclusivity, | J92: =IF(ISTEXT(F92), 1, 0) -> 1 | K92: =IF(ISTEXT(G92), 1, 0) -> 0 | L92: =IF(ISTEXT(H92), 1, 0) -> 0 | M92: =IF(ISTEXT(I92), 1, 0) -> 0 | N92: =SUM(J92:M92) -> 1
A93: P92 | B93: Along the Margins: Marginalized Communities’ Ethical Concerns about Social Platforms | C93: Lauren Olson, Emitzá Guzmán, Florian Kunneman | D93: 2023 | F93: marginalized communities, ethical concerns, privacy, misinformation, discrimination | I93: development practices | J93: =IF(ISTEXT(F93), 1, 0) -> 1 | K93: =IF(ISTEXT(G93), 1, 0) -> 0 | L93: =IF(ISTEXT(H93), 1, 0) -> 0 | M93: =IF(ISTEXT(I93), 1, 0) -> 1 | N93: =SUM(J93:M93) -> 2
A94: P93 | B94: Do Users Act Equitably? Understanding User Bias Through a Large In-person Study | C94: Yang Liu, Heather Moses, Mark Sternefeld, Samuel Malachowsky, Daniel E. Krutz | D94: 2023 | F94: inequity, software ethics, AI/ML bias | I94: AI?ML bias | J94: =IF(ISTEXT(F94), 1, 0) -> 1 | K94: =IF(ISTEXT(G94), 1, 0) -> 0 | L94: =IF(ISTEXT(H94), 1, 0) -> 0 | M94: =IF(ISTEXT(I94), 1, 0) -> 1 | N94: =SUM(J94:M94) -> 2
A95: P94 | B95: Developing Software for Low Socio-Economic End Users: Lessons Learned from A Case Study of Fisherfolk Communities in Bangladesh | C95: Tanjila Kanij, Misita Zhan, Md Khalid Hossain, Adnan Abdul-Mageed | D95: 2023 | F95: low socio-economic background, digital literacy, | I95: prototyping for tacit knowledge transfer | J95: =IF(ISTEXT(F95), 1, 0) -> 1 | K95: =IF(ISTEXT(G95), 1, 0) -> 0 | L95: =IF(ISTEXT(H95), 1, 0) -> 0 | M95: =IF(ISTEXT(I95), 1, 0) -> 1 | N95: =SUM(J95:M95) -> 2
A96: P95 | B96: Walking Down the Road to Independent Mobility: An Adaptive Route Training System for the Cognitively Impaired | C96: Konstantin Rink, Tristan Gruschka, Gudrun Dobslaw | D96: 2023 | F96: mobility training, inclusive design, conginitive impairments, | I96: inclusive design practices | J96: =IF(ISTEXT(F96), 1, 0) -> 1 | K96: =IF(ISTEXT(G96), 1, 0) -> 0 | L96: =IF(ISTEXT(H96), 1, 0) -> 0 | M96: =IF(ISTEXT(I96), 1, 0) -> 1 | N96: =SUM(J96:M96) -> 2
A97: P96 | B97: Diversity Awareness in Software Engineering Participant Research | C97: Riya Dutta, Diego Elias Costa, Emad Shihab, Torsten Tajmel | D97: 2023 | F97: diversity | J97: =IF(ISTEXT(F97), 1, 0) -> 1 | K97: =IF(ISTEXT(G97), 1, 0) -> 0 | L97: =IF(ISTEXT(H97), 1, 0) -> 0 | M97: =IF(ISTEXT(I97), 1, 0) -> 0 | N97: =SUM(J97:M97) -> 1
A98: P97 | B98: Harmful Terms in Computing: Towards Widespread Detection and Correction | C98: Hana Winchester, Alicia E. Boyd, Brittany Johnson | D98: 2023 | F98: Community Enhancing | J98: =IF(ISTEXT(F98), 1, 0) -> 1 | K98: =IF(ISTEXT(G98), 1, 0) -> 0 | L98: =IF(ISTEXT(H98), 1, 0) -> 0 | M98: =IF(ISTEXT(I98), 1, 0) -> 0 | N98: =SUM(J98:M98) -> 1
A99: P98 | B99: Metamorphic Testing and Debugging of Tax Preparation Software | C99: Saeid Tizpaz-Niari, Verya Monjezi, Markus Wagner, Sam Darian, Kimberly Reed, Ashutosh Trivedi | D99: 2023 | F99: Access and Equity | G99: Cost Efficiency | I99: maintainability | J99: =IF(ISTEXT(F99), 1, 0) -> 1 | K99: =IF(ISTEXT(G99), 1, 0) -> 1 | L99: =IF(ISTEXT(H99), 1, 0) -> 0 | M99: =IF(ISTEXT(I99), 1, 0) -> 1 | N99: =SUM(J99:M99) -> 3
A100: P99 | B100: Treat societally impactful scientific insights as open-source software artifacts | C100: Cynthia C. S. Liem, Andrew M. Demetriou | D100: 2023 | F100: Access and Equity | G100: efficient resource use | I100: long-term usability | J100: =IF(ISTEXT(F100), 1, 0) -> 1 | K100: =IF(ISTEXT(G100), 1, 0) -> 1 | L100: =IF(ISTEXT(H100), 1, 0) -> 0 | M100: =IF(ISTEXT(I100), 1, 0) -> 1 | N100: =SUM(J100:M100) -> 3
...
